[{"c":52000,"h":52000,"l":52000,"o":52000,"bu":100,"val_bu":5200000,"total_vol":100,"sum_vol":100,"val":5200000,"acum_val":5200000,"datetime":1676365800000,"date":"2023-02-14T09:10:00.000Z","pbu":100,"psd":0,"puk":0,"bs":null,"sb":0,"abu":66.7,"asd":266.7,"auk":0,"rbu":1.5,"bu-sd":100,"bu-sd_val":5200000,"avg_val_bu":3363333.3,"avg_val_sd":10800000,"acum_busd":100,"acum_busd_val":5200000,"acum_val_bu":5200000,"acum_val_sd":0,"rbusd":-0.7},{"c":40100,"h":40900,"l":40100,"o":40900,"sd":800,"val_sd":32400000,"total_vol":900,"sum_vol":800,"val":32400000,"acum_val":37600000,"datetime":1676384100000,"date":"2023-02-14T14:15:00.000Z","pbu":0,"psd":100,"puk":0,"bs":0,"sb":null,"abu":66.7,"asd":266.7,"auk":0,"rsd":3,"bu-sd":-800,"bu-sd_val":-32400000,"avg_val_bu":3363333.3,"avg_val_sd":10800000,"acum_busd":-700,"acum_busd_val":-27200000,"acum_val_bu":5200000,"acum_val_sd":32400000,"rbusd":4.4},{"c":48900,"h":48900,"l":48900,"o":48900,"bu":100,"val_bu":4890000,"total_vol":1000,"sum_vol":100,"val":4890000,"acum_val":42490000,"datetime":1676386500000,"date":"2023-02-14T14:55:00.000Z","pbu":100,"psd":0,"puk":0,"bs":null,"sb":0,"abu":66.7,"asd":266.7,"auk":0,"rbu":1.5,"bu-sd":100,"bu-sd_val":4890000,"avg_val_bu":3363333.3,"avg_val_sd":10800000,"acum_busd":-600,"acum_busd_val":-22310000,"acum_val_bu":10090000,"acum_val_sd":32400000,"rbusd":-0.7}]