<?xml version="1.0" encoding="utf-8"?>
<Subtitle>
  <Paragraph>
    <Number>1</Number>
    <StartMilliseconds>0</StartMilliseconds>
    <EndMilliseconds>3631</EndMilliseconds>
    <Text>[g@Wukong and Bajie looked all around.</Text>
  </Paragraph>
  <Paragraph>
    <Number>2</Number>
    <StartMilliseconds>3632</StartMilliseconds>
    <EndMilliseconds>6392</EndMilliseconds>
    <Text>But the Tang Monk was gone.@g]</Text>
  </Paragraph>
  <Paragraph>
    <Number>3</Number>
    <StartMilliseconds>6393</StartMilliseconds>
    <EndMilliseconds>11916</EndMilliseconds>
    <Text>"That tiger ate our master," said Bajie. He shrugged.</Text>
  </Paragraph>
  <Paragraph>
    <Number>4</Number>
    <StartMilliseconds>11917</StartMilliseconds>
    <EndMilliseconds>18283</EndMilliseconds>
    <Text>"I guess we don't have to protect him anymore. Good-bye, Wukong!"</Text>
  </Paragraph>
  <Paragraph>
    <Number>5</Number>
    <StartMilliseconds>18284</StartMilliseconds>
    <EndMilliseconds>21072</EndMilliseconds>
    <Text>[g@The pig started to walk away.</Text>
  </Paragraph>
  <Paragraph>
    <Number>6</Number>
    <StartMilliseconds>21073</StartMilliseconds>
    <EndMilliseconds>23339</EndMilliseconds>
    <Text>But Wukong grabbed him.@g]</Text>
  </Paragraph>
  <Paragraph>
    <Number>7</Number>
    <StartMilliseconds>23340</StartMilliseconds>
    <EndMilliseconds>26187</EndMilliseconds>
    <Text>[g@"You're not leaving!" said the monkey.</Text>
  </Paragraph>
  <Paragraph>
    <Number>8</Number>
    <StartMilliseconds>26188</StartMilliseconds>
    <EndMilliseconds>28598</EndMilliseconds>
    <Text>"We have to save our master.@g]</Text>
  </Paragraph>
  <Paragraph>
    <Number>9</Number>
    <StartMilliseconds>28599</StartMilliseconds>
    <EndMilliseconds>33486</EndMilliseconds>
    <Text>That tiger said he works for a demon, the great king Yellow Wind.</Text>
  </Paragraph>
  <Paragraph>
    <Number>10</Number>
    <StartMilliseconds>33487</StartMilliseconds>
    <EndMilliseconds>39047</EndMilliseconds>
    <Text>The king's cave must be nearby."</Text>
  </Paragraph>
  <Paragraph>
    <Number>11</Number>
    <StartMilliseconds>39048</StartMilliseconds>
    <EndMilliseconds>42350</EndMilliseconds>
    <Text>The tiger entered his master's cave.</Text>
  </Paragraph>
  <Paragraph>
    <Number>12</Number>
    <StartMilliseconds>42351</StartMilliseconds>
    <EndMilliseconds>46928</EndMilliseconds>
    <Text>The Tang Monk was slumped over the tiger's shoulder.</Text>
  </Paragraph>
  <Paragraph>
    <Number>13</Number>
    <StartMilliseconds>46929</StartMilliseconds>
    <EndMilliseconds>51731</EndMilliseconds>
    <Text>The great king Yellow Wind was sitting on his throne.</Text>
  </Paragraph>
  <Paragraph>
    <Number>14</Number>
    <StartMilliseconds>51732</StartMilliseconds>
    <EndMilliseconds>57963</EndMilliseconds>
    <Text>"Great king!" cried the tiger. "I found the Tang Monk!"</Text>
  </Paragraph>
  <Paragraph>
    <Number>15</Number>
    <StartMilliseconds>57964</StartMilliseconds>
    <EndMilliseconds>61538</EndMilliseconds>
    <Text>The demon king looked surprised and happy.</Text>
  </Paragraph>
  <Paragraph>
    <Number>16</Number>
    <StartMilliseconds>61539</StartMilliseconds>
    <EndMilliseconds>66250</EndMilliseconds>
    <Text>"I have heard that anyone who eats the Tang Monk will live forever.</Text>
  </Paragraph>
  <Paragraph>
    <Number>17</Number>
    <StartMilliseconds>66251</StartMilliseconds>
    <EndMilliseconds>68993</EndMilliseconds>
    <Text>Was the monk alone?"</Text>
  </Paragraph>
  <Paragraph>
    <Number>18</Number>
    <StartMilliseconds>68994</StartMilliseconds>
    <EndMilliseconds>72542</EndMilliseconds>
    <Text>"He had two companions," said the tiger.</Text>
  </Paragraph>
  <Paragraph>
    <Number>19</Number>
    <StartMilliseconds>72543</StartMilliseconds>
    <EndMilliseconds>74059</EndMilliseconds>
    <Text>[g@"One is a pig.</Text>
  </Paragraph>
  <Paragraph>
    <Number>20</Number>
    <StartMilliseconds>74060</StartMilliseconds>
    <EndMilliseconds>76930</EndMilliseconds>
    <Text>The other is a monkey."@g]</Text>
  </Paragraph>
  <Paragraph>
    <Number>21</Number>
    <StartMilliseconds>76931</StartMilliseconds>
    <EndMilliseconds>81539</EndMilliseconds>
    <Text>Yellow Wind trembled. "A monkey?" he said.</Text>
  </Paragraph>
  <Paragraph>
    <Number>22</Number>
    <StartMilliseconds>81540</StartMilliseconds>
    <EndMilliseconds>87809</EndMilliseconds>
    <Text>"He must be Sun Wukong—the monkey who caused all that trouble in Heaven!"</Text>
  </Paragraph>
  <Paragraph>
    <Number>23</Number>
    <StartMilliseconds>87810</StartMilliseconds>
    <EndMilliseconds>93027</EndMilliseconds>
    <Text>"Maybe," said the tiger. "But don't worry.</Text>
  </Paragraph>
  <Paragraph>
    <Number>24</Number>
    <StartMilliseconds>93028</StartMilliseconds>
    <EndMilliseconds>96822</EndMilliseconds>
    <Text>[g@I distracted them with a fake tiger skin.</Text>
  </Paragraph>
  <Paragraph>
    <Number>25</Number>
    <StartMilliseconds>96823</StartMilliseconds>
    <EndMilliseconds>100024</EndMilliseconds>
    <Text>They'll never find us."@g]</Text>
  </Paragraph>
  <Paragraph>
    <Number>26</Number>
    <StartMilliseconds>100025</StartMilliseconds>
    <EndMilliseconds>104196</EndMilliseconds>
    <Text>The tiger patted his stomach and looked at the Tang Monk.</Text>
  </Paragraph>
  <Paragraph>
    <Number>27</Number>
    <StartMilliseconds>104197</StartMilliseconds>
    <EndMilliseconds>109442</EndMilliseconds>
    <Text>"I'll tell the other demons to start a fire and prepare some spices."</Text>
  </Paragraph>
  <Paragraph>
    <Number>28</Number>
    <StartMilliseconds>109443</StartMilliseconds>
    <EndMilliseconds>112871</EndMilliseconds>
    <Text>[g@Yellow Wind held up his hand.</Text>
  </Paragraph>
  <Paragraph>
    <Number>29</Number>
    <StartMilliseconds>112872</StartMilliseconds>
    <EndMilliseconds>115591</EndMilliseconds>
    <Text>"Sun Wukong is powerful.@g]</Text>
  </Paragraph>
  <Paragraph>
    <Number>30</Number>
    <StartMilliseconds>115592</StartMilliseconds>
    <EndMilliseconds>119808</EndMilliseconds>
    <Text>He and that pig might come looking for the monk.</Text>
  </Paragraph>
  <Paragraph>
    <Number>31</Number>
    <StartMilliseconds>119809</StartMilliseconds>
    <EndMilliseconds>123389</EndMilliseconds>
    <Text>They'll be angry if they find out we ate him.</Text>
  </Paragraph>
  <Paragraph>
    <Number>32</Number>
    <StartMilliseconds>123390</StartMilliseconds>
    <EndMilliseconds>126850</EndMilliseconds>
    <Text>Let's wait until they leave the area.</Text>
  </Paragraph>
  <Paragraph>
    <Number>33</Number>
    <StartMilliseconds>126851</StartMilliseconds>
    <EndMilliseconds>130765</EndMilliseconds>
    <Text>Then we'll be able to enjoy our meal."</Text>
  </Paragraph>
  <Paragraph>
    <Number>34</Number>
    <StartMilliseconds>130766</StartMilliseconds>
    <EndMilliseconds>136631</EndMilliseconds>
    <Text>[g@A small demon ran into the throne room.</Text>
  </Paragraph>
  <Paragraph>
    <Number>35</Number>
    <StartMilliseconds>136632</StartMilliseconds>
    <EndMilliseconds>139960</EndMilliseconds>
    <Text>"Great king!" cried the demon.@g]</Text>
  </Paragraph>
  <Paragraph>
    <Number>36</Number>
    <StartMilliseconds>139961</StartMilliseconds>
    <EndMilliseconds>144777</EndMilliseconds>
    <Text>"There are two strangers outside—a monkey and a pig.</Text>
  </Paragraph>
  <Paragraph>
    <Number>37</Number>
    <StartMilliseconds>144778</StartMilliseconds>
    <EndMilliseconds>147403</EndMilliseconds>
    <Text>They said to hand over the Tang Monk.</Text>
  </Paragraph>
  <Paragraph>
    <Number>38</Number>
    <StartMilliseconds>147404</StartMilliseconds>
    <EndMilliseconds>152468</EndMilliseconds>
    <Text>If we don't, they'll destroy our entire mountain!"</Text>
  </Paragraph>
  <Paragraph>
    <Number>39</Number>
    <StartMilliseconds>152469</StartMilliseconds>
    <EndMilliseconds>158218</EndMilliseconds>
    <Text>"Oh no," moaned Yellow Wind. "This is bad!"</Text>
  </Paragraph>
  <Paragraph>
    <Number>40</Number>
    <StartMilliseconds>158219</StartMilliseconds>
    <EndMilliseconds>161258</EndMilliseconds>
    <Text>[g@"Don't worry, King," said the tiger.</Text>
  </Paragraph>
  <Paragraph>
    <Number>41</Number>
    <StartMilliseconds>161259</StartMilliseconds>
    <EndMilliseconds>164629</EndMilliseconds>
    <Text>"I will get rid of them."@g]</Text>
  </Paragraph>
  <Paragraph>
    <Number>42</Number>
    <StartMilliseconds>164630</StartMilliseconds>
    <EndMilliseconds>167801</EndMilliseconds>
    <Text>[g@The tiger walked out of the throne room.</Text>
  </Paragraph>
  <Paragraph>
    <Number>43</Number>
    <StartMilliseconds>167802</StartMilliseconds>
    <EndMilliseconds>173865</EndMilliseconds>
    <Text>The small demon followed him.@g]</Text>
  </Paragraph>
  <Paragraph>
    <Number>44</Number>
    <StartMilliseconds>173866</StartMilliseconds>
    <EndMilliseconds>179659</EndMilliseconds>
    <Text>Outside the cave there was some yelling and then a crashing sound.</Text>
  </Paragraph>
  <Paragraph>
    <Number>45</Number>
    <StartMilliseconds>179660</StartMilliseconds>
    <EndMilliseconds>184002</EndMilliseconds>
    <Text>A moment later the small demon ran back in.</Text>
  </Paragraph>
  <Paragraph>
    <Number>46</Number>
    <StartMilliseconds>184003</StartMilliseconds>
    <EndMilliseconds>187345</EndMilliseconds>
    <Text>"Great king, disaster!" he cried.</Text>
  </Paragraph>
  <Paragraph>
    <Number>47</Number>
    <StartMilliseconds>187346</StartMilliseconds>
    <EndMilliseconds>189547</EndMilliseconds>
    <Text>[g@"The tiger is dead!</Text>
  </Paragraph>
  <Paragraph>
    <Number>48</Number>
    <StartMilliseconds>189548</StartMilliseconds>
    <EndMilliseconds>192553</EndMilliseconds>
    <Text>The pig killed him with his rake!"@g]</Text>
  </Paragraph>
  <Paragraph>
    <Number>49</Number>
    <StartMilliseconds>192554</StartMilliseconds>
    <EndMilliseconds>195338</EndMilliseconds>
    <Text>[g@"What?" cried Yellow Wind.</Text>
  </Paragraph>
  <Paragraph>
    <Number>50</Number>
    <StartMilliseconds>195339</StartMilliseconds>
    <EndMilliseconds>200837</EndMilliseconds>
    <Text>He stood up and grabbed a trident.@g]</Text>
  </Paragraph>
  <Paragraph>
    <Number>51</Number>
    <StartMilliseconds>200838</StartMilliseconds>
    <EndMilliseconds>205839</EndMilliseconds>
    <Text>[g@He puffed out his chest and stomped out of the cave.</Text>
  </Paragraph>
  <Paragraph>
    <Number>52</Number>
    <StartMilliseconds>205840</StartMilliseconds>
    <EndMilliseconds>208109</EndMilliseconds>
    <Text>He saw Wukong.@g]</Text>
  </Paragraph>
  <Paragraph>
    <Number>53</Number>
    <StartMilliseconds>208110</StartMilliseconds>
    <EndMilliseconds>214185</EndMilliseconds>
    <Text>"So you're the monkey who caused all the [n@trouble in Heaven," said Yellow Wind.</Text>
  </Paragraph>
  <Paragraph>
    <Number>54</Number>
    <StartMilliseconds>214186</StartMilliseconds>
    <EndMilliseconds>218011</EndMilliseconds>
    <Text>"Hand over the Tang Monk!" demanded Wukong.</Text>
  </Paragraph>
  <Paragraph>
    <Number>55</Number>
    <StartMilliseconds>218012</StartMilliseconds>
    <EndMilliseconds>223360</EndMilliseconds>
    <Text>"I didn't know you were so small," said Yellow Wind.</Text>
  </Paragraph>
  <Paragraph>
    <Number>56</Number>
    <StartMilliseconds>223361</StartMilliseconds>
    <EndMilliseconds>225805</EndMilliseconds>
    <Text>[g@"Hit me on the head," said the monkey.</Text>
  </Paragraph>
  <Paragraph>
    <Number>57</Number>
    <StartMilliseconds>225806</StartMilliseconds>
    <EndMilliseconds>227666</EndMilliseconds>
    <Text>"I'll grow bigger."@g]</Text>
  </Paragraph>
  <Paragraph>
    <Number>58</Number>
    <StartMilliseconds>227667</StartMilliseconds>
    <EndMilliseconds>230110</EndMilliseconds>
    <Text>The demon king hesitated.</Text>
  </Paragraph>
  <Paragraph>
    <Number>59</Number>
    <StartMilliseconds>230111</StartMilliseconds>
    <EndMilliseconds>233459</EndMilliseconds>
    <Text>"Go ahead!" said Wukong.</Text>
  </Paragraph>
  <Paragraph>
    <Number>60</Number>
    <StartMilliseconds>233460</StartMilliseconds>
    <EndMilliseconds>237130</EndMilliseconds>
    <Text>[g@Yellow Wind knocked the monkey on the head.</Text>
  </Paragraph>
  <Paragraph>
    <Number>61</Number>
    <StartMilliseconds>237131</StartMilliseconds>
    <EndMilliseconds>240171</EndMilliseconds>
    <Text>Instantly Wukong grew tall.@g]</Text>
  </Paragraph>
  <Paragraph>
    <Number>62</Number>
    <StartMilliseconds>240172</StartMilliseconds>
    <EndMilliseconds>243693</EndMilliseconds>
    <Text>[g@"Now I'll hit you!" cried Wukong.</Text>
  </Paragraph>
  <Paragraph>
    <Number>63</Number>
    <StartMilliseconds>243694</StartMilliseconds>
    <EndMilliseconds>247094</EndMilliseconds>
    <Text>He swung his iron bar.@g]</Text>
  </Paragraph>
  <Paragraph>
    <Number>64</Number>
    <StartMilliseconds>247095</StartMilliseconds>
    <EndMilliseconds>251529</EndMilliseconds>
    <Text>[i@Crash!@i] The demon king blocked the bar with his trident.</Text>
  </Paragraph>
  <Paragraph>
    <Number>65</Number>
    <StartMilliseconds>251530</StartMilliseconds>
    <EndMilliseconds>257314</EndMilliseconds>
    <Text>[i@Clang!@i] The two fought up and down the side of the mountain.</Text>
  </Paragraph>
  <Paragraph>
    <Number>66</Number>
    <StartMilliseconds>257315</StartMilliseconds>
    <EndMilliseconds>260070</EndMilliseconds>
    <Text>"I'll use some magic," thought the monkey.</Text>
  </Paragraph>
  <Paragraph>
    <Number>67</Number>
    <StartMilliseconds>260071</StartMilliseconds>
    <EndMilliseconds>264960</EndMilliseconds>
    <Text>He grabbed a handful of hair and blew on it.</Text>
  </Paragraph>
  <Paragraph>
    <Number>68</Number>
    <StartMilliseconds>264961</StartMilliseconds>
    <EndMilliseconds>269400</EndMilliseconds>
    <Text>Dozens of little Wukongs ran toward the demon king.</Text>
  </Paragraph>
  <Paragraph>
    <Number>69</Number>
    <StartMilliseconds>269401</StartMilliseconds>
    <EndMilliseconds>275653</EndMilliseconds>
    <Text>Yellow Wind laughed. "I know a magic trick too!"</Text>
  </Paragraph>
  <Paragraph>
    <Number>70</Number>
    <StartMilliseconds>275654</StartMilliseconds>
    <EndMilliseconds>283936</EndMilliseconds>
    <Text>He looked down and blew three times.</Text>
  </Paragraph>
  <Paragraph>
    <Number>71</Number>
    <StartMilliseconds>283937</StartMilliseconds>
    <EndMilliseconds>286191</EndMilliseconds>
    <Text>[g@The sky grew dark.</Text>
  </Paragraph>
  <Paragraph>
    <Number>72</Number>
    <StartMilliseconds>286192</StartMilliseconds>
    <EndMilliseconds>290202</EndMilliseconds>
    <Text>A powerful yellow wind whipped across the mountain.@g]</Text>
  </Paragraph>
  <Paragraph>
    <Number>73</Number>
    <StartMilliseconds>290203</StartMilliseconds>
    <EndMilliseconds>293583</EndMilliseconds>
    <Text>Trees snapped and rocks tumbled.</Text>
  </Paragraph>
  <Paragraph>
    <Number>74</Number>
    <StartMilliseconds>293584</StartMilliseconds>
    <EndMilliseconds>298768</EndMilliseconds>
    <Text>Wukong, Bajie, and all the little Wukongs tumbled down the mountain.</Text>
  </Paragraph>
  <Paragraph>
    <Number>75</Number>
    <StartMilliseconds>298769</StartMilliseconds>
    <EndMilliseconds>307750</EndMilliseconds>
    <Text>They landed at the bottom in a cloud of dust.</Text>
  </Paragraph>
  <Paragraph>
    <Number>76</Number>
    <StartMilliseconds>307751</StartMilliseconds>
    <EndMilliseconds>317697</EndMilliseconds>
    <Text>The demon king went back into his cave and slammed the door shut.</Text>
  </Paragraph>
</Subtitle>