[{"c":700,"h":700,"l":700,"o":700,"bu":10100,"val_bu":7070000,"total_vol":10100,"sum_vol":10100,"val":7070000,"acum_val":7070000,"datetime":1677204000000,"date":"2023-02-24T02:00:00.000Z","pbu":100,"psd":0,"puk":0,"bs":null,"sb":0,"abu":4217.6,"asd":0,"auk":0,"rbu":2.4,"bu-sd":10100,"bu-sd_val":7070000,"avg_val_bu":2952352.9,"avg_val_sd":0,"acum_busd":10100,"acum_busd_val":7070000,"acum_val_bu":7070000,"acum_val_sd":0,"rbusd":2.4},{"c":700,"h":700,"l":700,"o":700,"bu":100,"val_bu":70000,"total_vol":10200,"sum_vol":100,"val":70000,"acum_val":7140000,"datetime":1677229200000,"date":"2023-02-24T09:00:00.000Z","pbu":100,"psd":0,"puk":0,"bs":null,"sb":0,"abu":4217.6,"asd":0,"auk":0,"rbu":0,"bu-sd":100,"bu-sd_val":70000,"avg_val_bu":2952352.9,"avg_val_sd":0,"acum_busd":10200,"acum_busd_val":7140000,"acum_val_bu":7140000,"acum_val_sd":0,"rbusd":0},{"c":700,"h":700,"l":700,"o":700,"bu":500,"val_bu":350000,"total_vol":10700,"sum_vol":500,"val":350000,"acum_val":7490000,"datetime":1677229500000,"date":"2023-02-24T09:05:00.000Z","pbu":100,"psd":0,"puk":0,"bs":null,"sb":0,"abu":4217.6,"asd":0,"auk":0,"rbu":0.1,"bu-sd":500,"bu-sd_val":350000,"avg_val_bu":2952352.9,"avg_val_sd":0,"acum_busd":10700,"acum_busd_val":7490000,"acum_val_bu":7490000,"acum_val_sd":0,"rbusd":0.1},{"c":700,"h":700,"l":700,"o":700,"bu":7200,"val_bu":5040000,"total_vol":17900,"sum_vol":7200,"val":5040000,"acum_val":12530000,"datetime":1677230100000,"date":"2023-02-24T09:15:00.000Z","pbu":100,"psd":0,"puk":0,"bs":null,"sb":0,"abu":4217.6,"asd":0,"auk":0,"rbu":1.7,"bu-sd":7200,"bu-sd_val":5040000,"avg_val_bu":2952352.9,"avg_val_sd":0,"acum_busd":17900,"acum_busd_val":12530000,"acum_val_bu":12530000,"acum_val_sd":0,"rbusd":1.7},{"c":700,"h":700,"l":700,"o":700,"bu":5700,"val_bu":3990000,"total_vol":23600,"sum_vol":5700,"val":3990000,"acum_val":16520000,"datetime":1677230400000,"date":"2023-02-24T09:20:00.000Z","pbu":100,"psd":0,"puk":0,"bs":null,"sb":0,"abu":4217.6,"asd":0,"auk":0,"rbu":1.4,"bu-sd":5700,"bu-sd_val":3990000,"avg_val_bu":2952352.9,"avg_val_sd":0,"acum_busd":23600,"acum_busd_val":16520000,"acum_val_bu":16520000,"acum_val_sd":0,"rbusd":1.4},{"c":700,"h":700,"l":700,"o":700,"bu":5800,"val_bu":4060000,"total_vol":29400,"sum_vol":5800,"val":4060000,"acum_val":20580000,"datetime":1677231000000,"date":"2023-02-24T09:30:00.000Z","pbu":100,"psd":0,"puk":0,"bs":null,"sb":0,"abu":4217.6,"asd":0,"auk":0,"rbu":1.4,"bu-sd":5800,"bu-sd_val":4060000,"avg_val_bu":2952352.9,"avg_val_sd":0,"acum_busd":29400,"acum_busd_val":20580000,"acum_val_bu":20580000,"acum_val_sd":0,"rbusd":1.4},{"c":700,"h":700,"l":700,"o":700,"bu":10000,"val_bu":7000000,"total_vol":39400,"sum_vol":10000,"val":7000000,"acum_val":27580000,"datetime":1677231900000,"date":"2023-02-24T09:45:00.000Z","pbu":100,"psd":0,"puk":0,"bs":null,"sb":0,"abu":4217.6,"asd":0,"auk":0,"rbu":2.4,"bu-sd":10000,"bu-sd_val":7000000,"avg_val_bu":2952352.9,"avg_val_sd":0,"acum_busd":39400,"acum_busd_val":27580000,"acum_val_bu":27580000,"acum_val_sd":0,"rbusd":2.4},{"c":700,"h":700,"l":700,"o":700,"bu":100,"val_bu":70000,"total_vol":39500,"sum_vol":100,"val":70000,"acum_val":27650000,"datetime":1677232200000,"date":"2023-02-24T09:50:00.000Z","pbu":100,"psd":0,"puk":0,"bs":null,"sb":0,"abu":4217.6,"asd":0,"auk":0,"rbu":0,"bu-sd":100,"bu-sd_val":70000,"avg_val_bu":2952352.9,"avg_val_sd":0,"acum_busd":39500,"acum_busd_val":27650000,"acum_val_bu":27650000,"acum_val_sd":0,"rbusd":0},{"c":700,"h":700,"l":700,"o":700,"bu":4600,"val_bu":3220000,"total_vol":44100,"sum_vol":4600,"val":3220000,"acum_val":30870000,"datetime":1677233100000,"date":"2023-02-24T10:05:00.000Z","pbu":100,"psd":0,"puk":0,"bs":null,"sb":0,"abu":4217.6,"asd":0,"auk":0,"rbu":1.1,"bu-sd":4600,"bu-sd_val":3220000,"avg_val_bu":2952352.9,"avg_val_sd":0,"acum_busd":44100,"acum_busd_val":30870000,"acum_val_bu":30870000,"acum_val_sd":0,"rbusd":1.1},{"c":700,"h":700,"l":700,"o":700,"bu":1000,"val_bu":700000,"total_vol":45100,"sum_vol":1000,"val":700000,"acum_val":31570000,"datetime":1677233400000,"date":"2023-02-24T10:10:00.000Z","pbu":100,"psd":0,"puk":0,"bs":null,"sb":0,"abu":4217.6,"asd":0,"auk":0,"rbu":0.2,"bu-sd":1000,"bu-sd_val":700000,"avg_val_bu":2952352.9,"avg_val_sd":0,"acum_busd":45100,"acum_busd_val":31570000,"acum_val_bu":31570000,"acum_val_sd":0,"rbusd":0.2},{"c":700,"h":700,"l":700,"o":700,"bu":200,"val_bu":140000,"total_vol":45300,"sum_vol":200,"val":140000,"acum_val":31710000,"datetime":1677235200000,"date":"2023-02-24T10:40:00.000Z","pbu":100,"psd":0,"puk":0,"bs":null,"sb":0,"abu":4217.6,"asd":0,"auk":0,"rbu":0,"bu-sd":200,"bu-sd_val":140000,"avg_val_bu":2952352.9,"avg_val_sd":0,"acum_busd":45300,"acum_busd_val":31710000,"acum_val_bu":31710000,"acum_val_sd":0,"rbusd":0},{"c":700,"h":700,"l":700,"o":700,"bu":14100,"val_bu":9870000,"total_vol":59400,"sum_vol":14100,"val":9870000,"acum_val":41580000,"datetime":1677236700000,"date":"2023-02-24T11:05:00.000Z","pbu":100,"psd":0,"puk":0,"bs":null,"sb":0,"abu":4217.6,"asd":0,"auk":0,"rbu":3.3,"bu-sd":14100,"bu-sd_val":9870000,"avg_val_bu":2952352.9,"avg_val_sd":0,"acum_busd":59400,"acum_busd_val":41580000,"acum_val_bu":41580000,"acum_val_sd":0,"rbusd":3.3},{"c":700,"h":700,"l":700,"o":700,"bu":9800,"val_bu":6860000,"total_vol":69200,"sum_vol":9800,"val":6860000,"acum_val":48440000,"datetime":1677237000000,"date":"2023-02-24T11:10:00.000Z","pbu":100,"psd":0,"puk":0,"bs":null,"sb":0,"abu":4217.6,"asd":0,"auk":0,"rbu":2.3,"bu-sd":9800,"bu-sd_val":6860000,"avg_val_bu":2952352.9,"avg_val_sd":0,"acum_busd":69200,"acum_busd_val":48440000,"acum_val_bu":48440000,"acum_val_sd":0,"rbusd":2.3},{"c":700,"h":700,"l":700,"o":700,"bu":1500,"val_bu":1050000,"total_vol":70700,"sum_vol":1500,"val":1050000,"acum_val":49490000,"datetime":1677237600000,"date":"2023-02-24T11:20:00.000Z","pbu":100,"psd":0,"puk":0,"bs":null,"sb":0,"abu":4217.6,"asd":0,"auk":0,"rbu":0.4,"bu-sd":1500,"bu-sd_val":1050000,"avg_val_bu":2952352.9,"avg_val_sd":0,"acum_busd":70700,"acum_busd_val":49490000,"acum_val_bu":49490000,"acum_val_sd":0,"rbusd":0.4},{"c":700,"h":700,"l":700,"o":700,"bu":300,"val_bu":210000,"total_vol":71000,"sum_vol":300,"val":210000,"acum_val":49700000,"datetime":1677243900000,"date":"2023-02-24T13:05:00.000Z","pbu":100,"psd":0,"puk":0,"bs":null,"sb":0,"abu":4217.6,"asd":0,"auk":0,"rbu":0.1,"bu-sd":300,"bu-sd_val":210000,"avg_val_bu":2952352.9,"avg_val_sd":0,"acum_busd":71000,"acum_busd_val":49700000,"acum_val_bu":49700000,"acum_val_sd":0,"rbusd":0.1},{"c":700,"h":700,"l":700,"o":700,"bu":600,"val_bu":420000,"total_vol":71600,"sum_vol":600,"val":420000,"acum_val":50120000,"datetime":1677247500000,"date":"2023-02-24T14:05:00.000Z","pbu":100,"psd":0,"puk":0,"bs":null,"sb":0,"abu":4217.6,"asd":0,"auk":0,"rbu":0.1,"bu-sd":600,"bu-sd_val":420000,"avg_val_bu":2952352.9,"avg_val_sd":0,"acum_busd":71600,"acum_busd_val":50120000,"acum_val_bu":50120000,"acum_val_sd":0,"rbusd":0.1},{"c":700,"h":700,"l":700,"o":700,"bu":100,"val_bu":70000,"total_vol":71700,"sum_vol":100,"val":70000,"acum_val":50190000,"datetime":1677249300000,"date":"2023-02-24T14:35:00.000Z","pbu":100,"psd":0,"puk":0,"bs":null,"sb":0,"abu":4217.6,"asd":0,"auk":0,"rbu":0,"bu-sd":100,"bu-sd_val":70000,"avg_val_bu":2952352.9,"avg_val_sd":0,"acum_busd":71700,"acum_busd_val":50190000,"acum_val_bu":50190000,"acum_val_sd":0,"rbusd":0}]
[{"c":800,"h":800,"l":800,"o":800,"bu":1300,"val_bu":1040000,"total_vol":1300,"sum_vol":1300,"val":1040000,"acum_val":1040000,"datetime":1676624400000,"date":"2023-02-17T09:00:00.000Z","pbu":100,"psd":0,"puk":0,"bs":null,"sb":0,"abu":1728.6,"asd":0,"auk":0,"rbu":0.8,"bu-sd":1300,"bu-sd_val":1040000,"avg_val_bu":1382857.1,"avg_val_sd":0,"acum_busd":1300,"acum_busd_val":1040000,"acum_val_bu":1040000,"acum_val_sd":0,"rbusd":0.8},{"c":800,"h":800,"l":800,"o":800,"bu":500,"val_bu":400000,"total_vol":1800,"sum_vol":500,"val":400000,"acum_val":1440000,"datetime":1676625300000,"date":"2023-02-17T09:15:00.000Z","pbu":100,"psd":0,"puk":0,"bs":null,"sb":0,"abu":1728.6,"asd":0,"auk":0,"rbu":0.3,"bu-sd":500,"bu-sd_val":400000,"avg_val_bu":1382857.1,"avg_val_sd":0,"acum_busd":1800,"acum_busd_val":1440000,"acum_val_bu":1440000,"acum_val_sd":0,"rbusd":0.3},{"c":800,"h":800,"l":800,"o":800,"bu":1000,"val_bu":800000,"total_vol":2800,"sum_vol":1000,"val":800000,"acum_val":2240000,"datetime":1676629200000,"date":"2023-02-17T10:20:00.000Z","pbu":100,"psd":0,"puk":0,"bs":null,"sb":0,"abu":1728.6,"asd":0,"auk":0,"rbu":0.6,"bu-sd":1000,"bu-sd_val":800000,"avg_val_bu":1382857.1,"avg_val_sd":0,"acum_busd":2800,"acum_busd_val":2240000,"acum_val_bu":2240000,"acum_val_sd":0,"rbusd":0.6},{"c":800,"h":800,"l":800,"o":800,"bu":1000,"val_bu":800000,"total_vol":3800,"sum_vol":1000,"val":800000,"acum_val":3040000,"datetime":1676629500000,"date":"2023-02-17T10:25:00.000Z","pbu":100,"psd":0,"puk":0,"bs":null,"sb":0,"abu":1728.6,"asd":0,"auk":0,"rbu":0.6,"bu-sd":1000,"bu-sd_val":800000,"avg_val_bu":1382857.1,"avg_val_sd":0,"acum_busd":3800,"acum_busd_val":3040000,"acum_val_bu":3040000,"acum_val_sd":0,"rbusd":0.6},{"c":800,"h":800,"l":800,"o":800,"bu":8000,"val_bu":6400000,"total_vol":11800,"sum_vol":8000,"val":6400000,"acum_val":9440000,"datetime":1676630400000,"date":"2023-02-17T10:40:00.000Z","pbu":100,"psd":0,"puk":0,"bs":null,"sb":0,"abu":1728.6,"asd":0,"auk":0,"rbu":4.6,"bu-sd":8000,"bu-sd_val":6400000,"avg_val_bu":1382857.1,"avg_val_sd":0,"acum_busd":11800,"acum_busd_val":9440000,"acum_val_bu":9440000,"acum_val_sd":0,"rbusd":4.6},{"c":800,"h":800,"l":800,"o":800,"bu":100,"val_bu":80000,"total_vol":11900,"sum_vol":100,"val":80000,"acum_val":9520000,"datetime":1676639700000,"date":"2023-02-17T13:15:00.000Z","pbu":100,"psd":0,"puk":0,"bs":null,"sb":0,"abu":1728.6,"asd":0,"auk":0,"rbu":0.1,"bu-sd":100,"bu-sd_val":80000,"avg_val_bu":1382857.1,"avg_val_sd":0,"acum_busd":11900,"acum_busd_val":9520000,"acum_val_bu":9520000,"acum_val_sd":0,"rbusd":0.1},{"c":800,"h":800,"l":800,"o":800,"bu":200,"val_bu":160000,"total_vol":12100,"sum_vol":200,"val":160000,"acum_val":9680000,"datetime":1676640300000,"date":"2023-02-17T13:25:00.000Z","pbu":100,"psd":0,"puk":0,"bs":null,"sb":0,"abu":1728.6,"asd":0,"auk":0,"rbu":0.1,"bu-sd":200,"bu-sd_val":160000,"avg_val_bu":1382857.1,"avg_val_sd":0,"acum_busd":12100,"acum_busd_val":9680000,"acum_val_bu":9680000,"acum_val_sd":0,"rbusd":0.1}]
[{"c":0.9,"h":1,"l":0.9,"o":1,"bu":110400,"val_bu":99270100,"total_vol":110400,"sum_vol":110400,"val":99270100,"acum_val":99270100,"datetime":1676020500000,"date":"2023-02-10T09:15:00.000Z","pbu":100,"psd":0,"puk":0,"bs":null,"sb":0,"abu":23700,"asd":1883.3,"auk":0,"rbu":4.7,"bu-sd":110400,"bu-sd_val":99270100,"avg_val_bu":21135216.7,"avg_val_sd":1695000,"acum_busd":110400,"acum_busd_val":99270100,"acum_val_bu":99270100,"acum_val_sd":0,"rbusd":5.1},{"c":0.9,"h":0.9,"l":0.9,"o":0.9,"bu":30600,"val_bu":27540000,"total_vol":141000,"sum_vol":30600,"val":27540000,"acum_val":126810100,"datetime":1676020800000,"date":"2023-02-10T09:20:00.000Z","pbu":100,"psd":0,"puk":0,"bs":null,"sb":0,"abu":23700,"asd":1883.3,"auk":0,"rbu":1.3,"bu-sd":30600,"bu-sd_val":27540000,"avg_val_bu":21135216.7,"avg_val_sd":1695000,"acum_busd":141000,"acum_busd_val":126810100,"acum_val_bu":126810100,"acum_val_sd":0,"rbusd":1.4},{"c":1,"h":1,"l":1,"o":1,"bu":1200,"val_bu":1200,"total_vol":142200,"sum_vol":1200,"val":1200,"acum_val":126811300,"datetime":1676023800000,"date":"2023-02-10T10:10:00.000Z","pbu":100,"psd":0,"puk":0,"bs":null,"sb":0,"abu":23700,"asd":1883.3,"auk":0,"rbu":0.1,"bu-sd":1200,"bu-sd_val":1200,"avg_val_bu":21135216.7,"avg_val_sd":1695000,"acum_busd":142200,"acum_busd_val":126811300,"acum_val_bu":126811300,"acum_val_sd":0,"rbusd":0},{"c":0.9,"h":0.9,"l":0.9,"o":0.9,"sd":10000,"val_sd":9000000,"total_vol":152200,"sum_vol":10000,"val":9000000,"acum_val":135811300,"datetime":1676034300000,"date":"2023-02-10T13:05:00.000Z","pbu":0,"psd":100,"puk":0,"bs":0,"sb":null,"abu":23700,"asd":1883.3,"auk":0,"rsd":5.3,"bu-sd":-10000,"bu-sd_val":-9000000,"avg_val_bu":21135216.7,"avg_val_sd":1695000,"acum_busd":132200,"acum_busd_val":117811300,"acum_val_bu":126811300,"acum_val_sd":9000000,"rbusd":-0.5},{"c":0.9,"h":0.9,"l":0.9,"o":0.9,"sd":100,"val_sd":90000,"total_vol":152300,"sum_vol":100,"val":90000,"acum_val":135901300,"datetime":1676034600000,"date":"2023-02-10T13:10:00.000Z","pbu":0,"psd":100,"puk":0,"bs":0,"sb":null,"abu":23700,"asd":1883.3,"auk":0,"rsd":0.1,"bu-sd":-100,"bu-sd_val":-90000,"avg_val_bu":21135216.7,"avg_val_sd":1695000,"acum_busd":132100,"acum_busd_val":117721300,"acum_val_bu":126811300,"acum_val_sd":9090000,"rbusd":0},{"c":0.9,"h":0.9,"l":0.9,"o":0.9,"sd":1200,"val_sd":1080000,"total_vol":153500,"sum_vol":1200,"val":1080000,"acum_val":136981300,"datetime":1676038200000,"date":"2023-02-10T14:10:00.000Z","pbu":0,"psd":100,"puk":0,"bs":0,"sb":null,"abu":23700,"asd":1883.3,"auk":0,"rsd":0.6,"bu-sd":-1200,"bu-sd_val":-1080000,"avg_val_bu":21135216.7,"avg_val_sd":1695000,"acum_busd":130900,"acum_busd_val":116641300,"acum_val_bu":126811300,"acum_val_sd":10170000,"rbusd":-0.1}]
[{"c":1,"h":1,"l":1,"o":1,"sd":500,"val_sd":500,"total_vol":500,"sum_vol":500,"val":500,"acum_val":500,"datetime":1675415100000,"date":"2023-02-03T09:05:00.000Z","pbu":0,"psd":100,"puk":0,"bs":0,"sb":null,"abu":0,"asd":800,"auk":0,"rsd":0.6,"bu-sd":-500,"bu-sd_val":-500,"avg_val_bu":0,"avg_val_sd":800,"acum_busd":-500,"acum_busd_val":-500,"acum_val_bu":0,"acum_val_sd":500,"rbusd":0.6},{"c":1,"h":1,"l":1,"o":1,"sd":1100,"val_sd":1100,"total_vol":1600,"sum_vol":1100,"val":1100,"acum_val":1600,"datetime":1675417200000,"date":"2023-02-03T09:40:00.000Z","pbu":0,"psd":100,"puk":0,"bs":0,"sb":null,"abu":0,"asd":800,"auk":0,"rsd":1.4,"bu-sd":-1100,"bu-sd_val":-1100,"avg_val_bu":0,"avg_val_sd":800,"acum_busd":-1600,"acum_busd_val":-1600,"acum_val_bu":0,"acum_val_sd":1600,"rbusd":1.4}]
[{"c":1.1,"h":1.1,"l":1.1,"o":1.1,"bu":100,"val_bu":110000.00000000001,"total_vol":100,"sum_vol":100,"val":110000.00000000001,"acum_val":110000.00000000001,"datetime":1675242300000,"date":"2023-02-01T09:05:00.000Z","pbu":100,"psd":0,"puk":0,"bs":null,"sb":0,"abu":1914.3,"asd":1985.7,"auk":0,"rbu":0.1,"bu-sd":100,"bu-sd_val":110000.00000000001,"avg_val_bu":1681814.3,"avg_val_sd":1985.7,"acum_busd":100,"acum_busd_val":110000.00000000001,"acum_val_bu":110000.00000000001,"acum_val_sd":0,"rbusd":0.1},{"c":1.1,"h":1.1,"l":1.1,"o":1.1,"bu":400,"val_bu":440000.00000000006,"total_vol":500,"sum_vol":400,"val":440000.00000000006,"acum_val":550000.0000000001,"datetime":1675243500000,"date":"2023-02-01T09:25:00.000Z","pbu":100,"psd":0,"puk":0,"bs":null,"sb":0,"abu":1914.3,"asd":1985.7,"auk":0,"rbu":0.2,"bu-sd":400,"bu-sd_val":440000.00000000006,"avg_val_bu":1681814.3,"avg_val_sd":1985.7,"acum_busd":500,"acum_busd_val":550000.0000000001,"acum_val_bu":550000.0000000001,"acum_val_sd":0,"rbusd":0.3},{"c":1.1,"h":1.1,"l":1.1,"o":1.1,"bu":100,"val_bu":110000.00000000001,"total_vol":600,"sum_vol":100,"val":110000.00000000001,"acum_val":660000.0000000001,"datetime":1675249200000,"date":"2023-02-01T11:00:00.000Z","pbu":100,"psd":0,"puk":0,"bs":null,"sb":0,"abu":1914.3,"asd":1985.7,"auk":0,"rbu":0.1,"bu-sd":100,"bu-sd_val":110000.00000000001,"avg_val_bu":1681814.3,"avg_val_sd":1985.7,"acum_busd":600,"acum_busd_val":660000.0000000001,"acum_val_bu":660000.0000000001,"acum_val_sd":0,"rbusd":0.1},{"c":1,"h":1,"l":1,"o":1,"sd":7600,"val_sd":7600,"total_vol":8700,"sum_vol":8100,"val":8100,"acum_val":668100.0000000001,"bu":500,"val_bu":500,"datetime":1675250400000,"date":"2023-02-01T11:20:00.000Z","pbu":6.2,"psd":93.8,"puk":0,"bs":0.1,"sb":15.2,"abu":1914.3,"asd":1985.7,"auk":0,"rsd":3.8,"rbu":0.3,"bu-sd":-7100,"bu-sd_val":-7100,"avg_val_bu":1681814.3,"avg_val_sd":1985.7,"acum_busd":-6500,"acum_busd_val":652900.0000000001,"acum_val_bu":660500.0000000001,"acum_val_sd":7600,"rbusd":0},{"c":1,"h":1,"l":1,"o":1,"bu":1900,"val_bu":1900,"total_vol":10600,"sum_vol":1900,"val":1900,"acum_val":670000.0000000001,"datetime":1675250700000,"date":"2023-02-01T11:25:00.000Z","pbu":100,"psd":0,"puk":0,"bs":null,"sb":0,"abu":1914.3,"asd":1985.7,"auk":0,"rbu":1,"bu-sd":1900,"bu-sd_val":1900,"avg_val_bu":1681814.3,"avg_val_sd":1985.7,"acum_busd":-4600,"acum_busd_val":654800.0000000001,"acum_val_bu":662400.0000000001,"acum_val_sd":7600,"rbusd":0},{"c":1,"h":1,"l":1,"o":1,"bu":300,"val_bu":300,"total_vol":17200,"sum_vol":6600,"val":6600,"acum_val":676600.0000000001,"sd":6300,"val_sd":6300,"datetime":1675258500000,"date":"2023-02-01T13:35:00.000Z","pbu":4.5,"psd":95.5,"puk":0,"bs":0,"sb":21,"abu":1914.3,"asd":1985.7,"auk":0,"rsd":3.2,"rbu":0.2,"bu-sd":-6000,"bu-sd_val":-6000,"avg_val_bu":1681814.3,"avg_val_sd":1985.7,"acum_busd":-10600,"acum_busd_val":648800.0000000001,"acum_val_bu":662700.0000000001,"acum_val_sd":13900,"rbusd":0},{"c":1.1,"h":1.1,"l":1.1,"o":1.1,"bu":10100,"val_bu":11110000,"total_vol":27300,"sum_vol":10100,"val":11110000,"acum_val":11786600,"datetime":1675261500000,"date":"2023-02-01T14:25:00.000Z","pbu":100,"psd":0,"puk":0,"bs":null,"sb":0,"abu":1914.3,"asd":1985.7,"auk":0,"rbu":5.3,"bu-sd":10100,"bu-sd_val":11110000,"avg_val_bu":1681814.3,"avg_val_sd":1985.7,"acum_busd":-500,"acum_busd_val":11758800,"acum_val_bu":11772700,"acum_val_sd":13900,"rbusd":6.6}]
[{"c":1.1,"h":1.1,"l":1.1,"o":1.1,"bu":100,"val_bu":110000.00000000001,"total_vol":100,"sum_vol":100,"val":110000.00000000001,"acum_val":110000.00000000001,"datetime":1674810300000,"date":"2023-01-27T09:05:00.000Z","pbu":100,"psd":0,"puk":0,"bs":null,"sb":0,"abu":1914.3,"asd":1985.7,"auk":0,"rbu":0.1,"bu-sd":100,"bu-sd_val":110000.00000000001,"avg_val_bu":1681814.3,"avg_val_sd":1985.7,"acum_busd":100,"acum_busd_val":110000.00000000001,"acum_val_bu":110000.00000000001,"acum_val_sd":0,"rbusd":0.1},{"c":1.1,"h":1.1,"l":1.1,"o":1.1,"bu":400,"val_bu":440000.00000000006,"total_vol":500,"sum_vol":400,"val":440000.00000000006,"acum_val":550000.0000000001,"datetime":1674811500000,"date":"2023-01-27T09:25:00.000Z","pbu":100,"psd":0,"puk":0,"bs":null,"sb":0,"abu":1914.3,"asd":1985.7,"auk":0,"rbu":0.2,"bu-sd":400,"bu-sd_val":440000.00000000006,"avg_val_bu":1681814.3,"avg_val_sd":1985.7,"acum_busd":500,"acum_busd_val":550000.0000000001,"acum_val_bu":550000.0000000001,"acum_val_sd":0,"rbusd":0.3},{"c":1.1,"h":1.1,"l":1.1,"o":1.1,"bu":100,"val_bu":110000.00000000001,"total_vol":600,"sum_vol":100,"val":110000.00000000001,"acum_val":660000.0000000001,"datetime":1674817200000,"date":"2023-01-27T11:00:00.000Z","pbu":100,"psd":0,"puk":0,"bs":null,"sb":0,"abu":1914.3,"asd":1985.7,"auk":0,"rbu":0.1,"bu-sd":100,"bu-sd_val":110000.00000000001,"avg_val_bu":1681814.3,"avg_val_sd":1985.7,"acum_busd":600,"acum_busd_val":660000.0000000001,"acum_val_bu":660000.0000000001,"acum_val_sd":0,"rbusd":0.1},{"c":1,"h":1,"l":1,"o":1,"sd":7600,"val_sd":7600,"total_vol":8700,"sum_vol":8100,"val":8100,"acum_val":668100.0000000001,"bu":500,"val_bu":500,"datetime":1674818400000,"date":"2023-01-27T11:20:00.000Z","pbu":6.2,"psd":93.8,"puk":0,"bs":0.1,"sb":15.2,"abu":1914.3,"asd":1985.7,"auk":0,"rsd":3.8,"rbu":0.3,"bu-sd":-7100,"bu-sd_val":-7100,"avg_val_bu":1681814.3,"avg_val_sd":1985.7,"acum_busd":-6500,"acum_busd_val":652900.0000000001,"acum_val_bu":660500.0000000001,"acum_val_sd":7600,"rbusd":0},{"c":1,"h":1,"l":1,"o":1,"bu":1900,"val_bu":1900,"total_vol":10600,"sum_vol":1900,"val":1900,"acum_val":670000.0000000001,"datetime":1674818700000,"date":"2023-01-27T11:25:00.000Z","pbu":100,"psd":0,"puk":0,"bs":null,"sb":0,"abu":1914.3,"asd":1985.7,"auk":0,"rbu":1,"bu-sd":1900,"bu-sd_val":1900,"avg_val_bu":1681814.3,"avg_val_sd":1985.7,"acum_busd":-4600,"acum_busd_val":654800.0000000001,"acum_val_bu":662400.0000000001,"acum_val_sd":7600,"rbusd":0},{"c":1,"h":1,"l":1,"o":1,"bu":300,"val_bu":300,"total_vol":17200,"sum_vol":6600,"val":6600,"acum_val":676600.0000000001,"sd":6300,"val_sd":6300,"datetime":1674826500000,"date":"2023-01-27T13:35:00.000Z","pbu":4.5,"psd":95.5,"puk":0,"bs":0,"sb":21,"abu":1914.3,"asd":1985.7,"auk":0,"rsd":3.2,"rbu":0.2,"bu-sd":-6000,"bu-sd_val":-6000,"avg_val_bu":1681814.3,"avg_val_sd":1985.7,"acum_busd":-10600,"acum_busd_val":648800.0000000001,"acum_val_bu":662700.0000000001,"acum_val_sd":13900,"rbusd":0},{"c":1.1,"h":1.1,"l":1.1,"o":1.1,"bu":10100,"val_bu":11110000,"total_vol":27300,"sum_vol":10100,"val":11110000,"acum_val":11786600,"datetime":1674829500000,"date":"2023-01-27T14:25:00.000Z","pbu":100,"psd":0,"puk":0,"bs":null,"sb":0,"abu":1914.3,"asd":1985.7,"auk":0,"rbu":5.3,"bu-sd":10100,"bu-sd_val":11110000,"avg_val_bu":1681814.3,"avg_val_sd":1985.7,"acum_busd":-500,"acum_busd_val":11758800,"acum_val_bu":11772700,"acum_val_sd":13900,"rbusd":6.6}]
[{"c":0.9,"h":0.9,"l":0.9,"o":0.9,"sd":1200,"val_sd":1080000,"total_vol":1200,"sum_vol":1200,"val":1080000,"acum_val":1080000,"datetime":1673607900000,"date":"2023-01-13T11:05:00.000Z","pbu":0,"psd":100,"puk":0,"bs":0,"sb":null,"abu":700,"asd":600,"auk":0,"rsd":2,"bu-sd":-1200,"bu-sd_val":-1080000,"avg_val_bu":700,"avg_val_sd":540000,"acum_busd":-1200,"acum_busd_val":-1080000,"acum_val_bu":0,"acum_val_sd":1080000,"rbusd":2},{"c":1,"h":1,"l":1,"o":1,"bu":1400,"val_bu":1400,"total_vol":2600,"sum_vol":1400,"val":1400,"acum_val":1081400,"datetime":1673619600000,"date":"2023-01-13T14:20:00.000Z","pbu":100,"psd":0,"puk":0,"bs":null,"sb":0,"abu":700,"asd":600,"auk":0,"rbu":2,"bu-sd":1400,"bu-sd_val":1400,"avg_val_bu":700,"avg_val_sd":540000,"acum_busd":200,"acum_busd_val":-1078600,"acum_val_bu":1400,"acum_val_sd":1080000,"rbusd":0}]
[{"c":1,"h":1,"l":1,"o":1,"sd":300,"val_sd":300,"total_vol":300,"sum_vol":300,"val":300,"acum_val":300,"datetime":1672997100000,"date":"2023-01-06T09:25:00.000Z","pbu":0,"psd":100,"puk":0,"bs":0,"sb":null,"abu":216.7,"asd":2216.7,"auk":0,"rsd":0.1,"bu-sd":-300,"bu-sd_val":-300,"avg_val_bu":216.7,"avg_val_sd":1245833.3,"acum_busd":-300,"acum_busd_val":-300,"acum_val_bu":0,"acum_val_sd":300,"rbusd":0},{"c":1,"h":1,"l":1,"o":1,"sd":4700,"val_sd":4700,"total_vol":5000,"sum_vol":4700,"val":4700,"acum_val":5000,"datetime":1673002500000,"date":"2023-01-06T10:55:00.000Z","pbu":0,"psd":100,"puk":0,"bs":0,"sb":null,"abu":216.7,"asd":2216.7,"auk":0,"rsd":2.1,"bu-sd":-4700,"bu-sd_val":-4700,"avg_val_bu":216.7,"avg_val_sd":1245833.3,"acum_busd":-5000,"acum_busd_val":-5000,"acum_val_bu":0,"acum_val_sd":5000,"rbusd":0},{"c":1,"h":1,"l":1,"o":1,"bu":200,"val_bu":200,"total_vol":5200,"sum_vol":200,"val":200,"acum_val":5200,"datetime":1673011500000,"date":"2023-01-06T13:25:00.000Z","pbu":100,"psd":0,"puk":0,"bs":null,"sb":0,"abu":216.7,"asd":2216.7,"auk":0,"rbu":0.9,"bu-sd":200,"bu-sd_val":200,"avg_val_bu":216.7,"avg_val_sd":1245833.3,"acum_busd":-4800,"acum_busd_val":-4800,"acum_val_bu":200,"acum_val_sd":5000,"rbusd":0},{"c":0.9,"h":0.9,"l":0.9,"o":0.9,"sd":8300,"val_sd":7470000,"total_vol":13500,"sum_vol":8300,"val":7470000,"acum_val":7475200,"datetime":1673014500000,"date":"2023-01-06T14:15:00.000Z","pbu":0,"psd":100,"puk":0,"bs":0,"sb":null,"abu":216.7,"asd":2216.7,"auk":0,"rsd":3.7,"bu-sd":-8300,"bu-sd_val":-7470000,"avg_val_bu":216.7,"avg_val_sd":1245833.3,"acum_busd":-13100,"acum_busd_val":-7474800,"acum_val_bu":200,"acum_val_sd":7475000,"rbusd":6},{"c":1,"h":1,"l":1,"o":1,"bu":100,"val_bu":100,"total_vol":13600,"sum_vol":100,"val":100,"acum_val":7475300,"datetime":1673016600000,"date":"2023-01-06T14:50:00.000Z","pbu":100,"psd":0,"puk":0,"bs":null,"sb":0,"abu":216.7,"asd":2216.7,"auk":0,"rbu":0.5,"bu-sd":100,"bu-sd_val":100,"avg_val_bu":216.7,"avg_val_sd":1245833.3,"acum_busd":-13000,"acum_busd_val":-7474700,"acum_val_bu":300,"acum_val_sd":7475000,"rbusd":0},{"c":1,"h":1,"l":1,"o":1,"bu":1000,"val_bu":1000,"total_vol":14600,"sum_vol":1000,"val":1000,"acum_val":7476300,"datetime":1673016900000,"date":"2023-01-06T14:55:00.000Z","pbu":100,"psd":0,"puk":0,"bs":null,"sb":0,"abu":216.7,"asd":2216.7,"auk":0,"rbu":4.6,"bu-sd":1000,"bu-sd_val":1000,"avg_val_bu":216.7,"avg_val_sd":1245833.3,"acum_busd":-12000,"acum_busd_val":-7473700,"acum_val_bu":1300,"acum_val_sd":7475000,"rbusd":0}]
[{"c":1,"h":1,"l":1,"o":1,"bu":200,"val_bu":200,"total_vol":200,"sum_vol":200,"val":200,"acum_val":200,"datetime":1672390800000,"date":"2022-12-30T09:00:00.000Z","pbu":100,"psd":0,"puk":0,"bs":null,"sb":0,"abu":4910,"asd":890,"auk":0,"rbu":0,"bu-sd":200,"bu-sd_val":200,"avg_val_bu":4910,"avg_val_sd":135740,"acum_busd":200,"acum_busd_val":200,"acum_val_bu":200,"acum_val_sd":0,"rbusd":0},{"c":0.9,"h":0.9,"l":0.9,"o":0.9,"sd":1100,"val_sd":990000,"total_vol":1300,"sum_vol":1100,"val":990000,"acum_val":990200,"datetime":1672393800000,"date":"2022-12-30T09:50:00.000Z","pbu":0,"psd":100,"puk":0,"bs":0,"sb":null,"abu":4910,"asd":890,"auk":0,"rsd":1.2,"bu-sd":-1100,"bu-sd_val":-990000,"avg_val_bu":4910,"avg_val_sd":135740,"acum_busd":-900,"acum_busd_val":-989800,"acum_val_bu":200,"acum_val_sd":990000,"rbusd":7.6},{"c":0.9,"h":0.9,"l":0.9,"o":0.9,"sd":400,"val_sd":360000,"total_vol":1700,"sum_vol":400,"val":360000,"acum_val":1350200,"datetime":1672395000000,"date":"2022-12-30T10:10:00.000Z","pbu":0,"psd":100,"puk":0,"bs":0,"sb":null,"abu":4910,"asd":890,"auk":0,"rsd":0.4,"bu-sd":-400,"bu-sd_val":-360000,"avg_val_bu":4910,"avg_val_sd":135740,"acum_busd":-1300,"acum_busd_val":-1349800,"acum_val_bu":200,"acum_val_sd":1350000,"rbusd":2.8},{"c":1,"h":1,"l":1,"o":1,"bu":32000,"val_bu":32000,"total_vol":33700,"sum_vol":32000,"val":32000,"acum_val":1382200,"datetime":1672397400000,"date":"2022-12-30T10:50:00.000Z","pbu":100,"psd":0,"puk":0,"bs":null,"sb":0,"abu":4910,"asd":890,"auk":0,"rbu":6.5,"bu-sd":32000,"bu-sd_val":32000,"avg_val_bu":4910,"avg_val_sd":135740,"acum_busd":30700,"acum_busd_val":-1317800,"acum_val_bu":32200,"acum_val_sd":1350000,"rbusd":-0.2},{"c":1,"h":1,"l":1,"o":1,"bu":11600,"val_bu":11600,"total_vol":45300,"sum_vol":11600,"val":11600,"acum_val":1393800,"datetime":1672397700000,"date":"2022-12-30T10:55:00.000Z","pbu":100,"psd":0,"puk":0,"bs":null,"sb":0,"abu":4910,"asd":890,"auk":0,"rbu":2.4,"bu-sd":11600,"bu-sd_val":11600,"avg_val_bu":4910,"avg_val_sd":135740,"acum_busd":42300,"acum_busd_val":-1306200,"acum_val_bu":43800,"acum_val_sd":1350000,"rbusd":-0.1},{"c":1,"h":1,"l":1,"o":1,"bu":800,"val_bu":800,"total_vol":46100,"sum_vol":800,"val":800,"acum_val":1394600,"datetime":1672405200000,"date":"2022-12-30T13:00:00.000Z","pbu":100,"psd":0,"puk":0,"bs":null,"sb":0,"abu":4910,"asd":890,"auk":0,"rbu":0.2,"bu-sd":800,"bu-sd_val":800,"avg_val_bu":4910,"avg_val_sd":135740,"acum_busd":43100,"acum_busd_val":-1305400,"acum_val_bu":44600,"acum_val_sd":1350000,"rbusd":0},{"c":1,"h":1,"l":1,"o":1,"bu":200,"val_bu":200,"total_vol":46300,"sum_vol":200,"val":200,"acum_val":1394800,"datetime":1672406100000,"date":"2022-12-30T13:15:00.000Z","pbu":100,"psd":0,"puk":0,"bs":null,"sb":0,"abu":4910,"asd":890,"auk":0,"rbu":0,"bu-sd":200,"bu-sd_val":200,"avg_val_bu":4910,"avg_val_sd":135740,"acum_busd":43300,"acum_busd_val":-1305200,"acum_val_bu":44800,"acum_val_sd":1350000,"rbusd":0},{"c":1,"h":1,"l":1,"o":1,"bu":1500,"val_bu":1500,"total_vol":47800,"sum_vol":1500,"val":1500,"acum_val":1396300,"datetime":1672406700000,"date":"2022-12-30T13:25:00.000Z","pbu":100,"psd":0,"puk":0,"bs":null,"sb":0,"abu":4910,"asd":890,"auk":0,"rbu":0.3,"bu-sd":1500,"bu-sd_val":1500,"avg_val_bu":4910,"avg_val_sd":135740,"acum_busd":44800,"acum_busd_val":-1303700,"acum_val_bu":46300,"acum_val_sd":1350000,"rbusd":0},{"c":1,"h":1,"l":1,"o":1,"bu":2000,"val_bu":2000,"total_vol":49800,"sum_vol":2000,"val":2000,"acum_val":1398300,"datetime":1672408800000,"date":"2022-12-30T14:00:00.000Z","pbu":100,"psd":0,"puk":0,"bs":null,"sb":0,"abu":4910,"asd":890,"auk":0,"rbu":0.4,"bu-sd":2000,"bu-sd_val":2000,"avg_val_bu":4910,"avg_val_sd":135740,"acum_busd":46800,"acum_busd_val":-1301700,"acum_val_bu":48300,"acum_val_sd":1350000,"rbusd":0},{"c":1,"h":1,"l":1,"o":1,"bu":800,"val_bu":800,"total_vol":58000,"sum_vol":8200,"val":8200,"acum_val":1406500,"sd":7400,"val_sd":7400,"datetime":1672409700000,"date":"2022-12-30T14:15:00.000Z","pbu":9.8,"psd":90.2,"puk":0,"bs":0.1,"sb":9.3,"abu":4910,"asd":890,"auk":0,"rsd":8.3,"rbu":0.2,"bu-sd":-6600,"bu-sd_val":-6600,"avg_val_bu":4910,"avg_val_sd":135740,"acum_busd":40200,"acum_busd_val":-1308300,"acum_val_bu":49100,"acum_val_sd":1357400,"rbusd":0.1}]
[{"c":1.1,"h":1.1,"l":1.1,"o":1.1,"bu":3400,"val_bu":3740000.0000000005,"total_vol":3400,"sum_vol":3400,"val":3740000.0000000005,"acum_val":3740000.0000000005,"datetime":1671786000000,"date":"2022-12-23T09:00:00.000Z","pbu":100,"psd":0,"puk":0,"bs":null,"sb":0,"abu":466.7,"asd":2944.4,"auk":0,"rbu":7.3,"bu-sd":3400,"bu-sd_val":3740000.0000000005,"avg_val_bu":415644.4,"avg_val_sd":2944.4,"acum_busd":3400,"acum_busd_val":3740000.0000000005,"acum_val_bu":3740000.0000000005,"acum_val_sd":0,"rbusd":9.1},{"c":1,"h":1,"l":1,"o":1,"sd":100,"val_sd":100,"total_vol":3500,"sum_vol":100,"val":100,"acum_val":3740100.0000000005,"datetime":1671793200000,"date":"2022-12-23T11:00:00.000Z","pbu":0,"psd":100,"puk":0,"bs":0,"sb":null,"abu":466.7,"asd":2944.4,"auk":0,"rsd":0,"bu-sd":-100,"bu-sd_val":-100,"avg_val_bu":415644.4,"avg_val_sd":2944.4,"acum_busd":3300,"acum_busd_val":3739900.0000000005,"acum_val_bu":3740000.0000000005,"acum_val_sd":100,"rbusd":0},{"c":1,"h":1,"l":1,"o":1,"sd":1900,"val_sd":1900,"total_vol":5400,"sum_vol":1900,"val":1900,"acum_val":3742000.0000000005,"datetime":1671800400000,"date":"2022-12-23T13:00:00.000Z","pbu":0,"psd":100,"puk":0,"bs":0,"sb":null,"abu":466.7,"asd":2944.4,"auk":0,"rsd":0.6,"bu-sd":-1900,"bu-sd_val":-1900,"avg_val_bu":415644.4,"avg_val_sd":2944.4,"acum_busd":1400,"acum_busd_val":3738000.0000000005,"acum_val_bu":3740000.0000000005,"acum_val_sd":2000,"rbusd":0},{"c":1,"h":1,"l":1,"o":1,"sd":3000,"val_sd":3000,"total_vol":8400,"sum_vol":3000,"val":3000,"acum_val":3745000.0000000005,"datetime":1671800700000,"date":"2022-12-23T13:05:00.000Z","pbu":0,"psd":100,"puk":0,"bs":0,"sb":null,"abu":466.7,"asd":2944.4,"auk":0,"rsd":1,"bu-sd":-3000,"bu-sd_val":-3000,"avg_val_bu":415644.4,"avg_val_sd":2944.4,"acum_busd":-1600,"acum_busd_val":3735000.0000000005,"acum_val_bu":3740000.0000000005,"acum_val_sd":5000,"rbusd":0},{"c":1,"h":1,"l":1,"o":1,"sd":1000,"val_sd":1000,"total_vol":9400,"sum_vol":1000,"val":1000,"acum_val":3746000.0000000005,"datetime":1671801300000,"date":"2022-12-23T13:15:00.000Z","pbu":0,"psd":100,"puk":0,"bs":0,"sb":null,"abu":466.7,"asd":2944.4,"auk":0,"rsd":0.3,"bu-sd":-1000,"bu-sd_val":-1000,"avg_val_bu":415644.4,"avg_val_sd":2944.4,"acum_busd":-2600,"acum_busd_val":3734000.0000000005,"acum_val_bu":3740000.0000000005,"acum_val_sd":6000,"rbusd":0},{"c":1,"h":1,"l":1,"o":1,"sd":100,"val_sd":100,"total_vol":9500,"sum_vol":100,"val":100,"acum_val":3746100.0000000005,"datetime":1671801600000,"date":"2022-12-23T13:20:00.000Z","pbu":0,"psd":100,"puk":0,"bs":0,"sb":null,"abu":466.7,"asd":2944.4,"auk":0,"rsd":0,"bu-sd":-100,"bu-sd_val":-100,"avg_val_bu":415644.4,"avg_val_sd":2944.4,"acum_busd":-2700,"acum_busd_val":3733900.0000000005,"acum_val_bu":3740000.0000000005,"acum_val_sd":6100,"rbusd":0},{"c":1,"h":1,"l":1,"o":1,"sd":20400,"val_sd":20400,"total_vol":30100,"sum_vol":20600,"val":20600,"acum_val":3766700.0000000005,"bu":200,"val_bu":200,"datetime":1671802200000,"date":"2022-12-23T13:30:00.000Z","pbu":1,"psd":99,"puk":0,"bs":0,"sb":102,"abu":466.7,"asd":2944.4,"auk":0,"rsd":6.9,"rbu":0.4,"bu-sd":-20200,"bu-sd_val":-20200,"avg_val_bu":415644.4,"avg_val_sd":2944.4,"acum_busd":-22900,"acum_busd_val":3713700.0000000005,"acum_val_bu":3740200.0000000005,"acum_val_sd":26500,"rbusd":0},{"c":1,"h":1,"l":1,"o":1,"bu":400,"val_bu":400,"total_vol":30500,"sum_vol":400,"val":400,"acum_val":3767100.0000000005,"datetime":1671804900000,"date":"2022-12-23T14:15:00.000Z","pbu":100,"psd":0,"puk":0,"bs":null,"sb":0,"abu":466.7,"asd":2944.4,"auk":0,"rbu":0.9,"bu-sd":400,"bu-sd_val":400,"avg_val_bu":415644.4,"avg_val_sd":2944.4,"acum_busd":-22500,"acum_busd_val":3714100.0000000005,"acum_val_bu":3740600.0000000005,"acum_val_sd":26500,"rbusd":0},{"c":1,"h":1,"l":1,"o":1,"bu":200,"val_bu":200,"total_vol":30700,"sum_vol":200,"val":200,"acum_val":3767300.0000000005,"datetime":1671805500000,"date":"2022-12-23T14:25:00.000Z","pbu":100,"psd":0,"puk":0,"bs":null,"sb":0,"abu":466.7,"asd":2944.4,"auk":0,"rbu":0.4,"bu-sd":200,"bu-sd_val":200,"avg_val_bu":415644.4,"avg_val_sd":2944.4,"acum_busd":-22300,"acum_busd_val":3714300.0000000005,"acum_val_bu":3740800.0000000005,"acum_val_sd":26500,"rbusd":0}]
[{"c":1.2,"h":1.2,"l":1.2,"o":1.2,"bu":13100,"val_bu":15720000,"total_vol":13100,"sum_vol":13100,"val":15720000,"acum_val":15720000,"datetime":1671181200000,"date":"2022-12-16T09:00:00.000Z","pbu":100,"psd":0,"puk":0,"bs":null,"sb":0,"abu":2078.6,"asd":1828.6,"auk":0,"rbu":6.3,"bu-sd":13100,"bu-sd_val":15720000,"avg_val_bu":2407857.1,"avg_val_sd":2003578.6,"acum_busd":13100,"acum_busd_val":15720000,"acum_val_bu":15720000,"acum_val_sd":0,"rbusd":38.9},{"c":1.2,"h":1.2,"l":1.2,"o":1.2,"bu":400,"val_bu":480000,"total_vol":13500,"sum_vol":400,"val":480000,"acum_val":16200000,"datetime":1671183000000,"date":"2022-12-16T09:30:00.000Z","pbu":100,"psd":0,"puk":0,"bs":null,"sb":0,"abu":2078.6,"asd":1828.6,"auk":0,"rbu":0.2,"bu-sd":400,"bu-sd_val":480000,"avg_val_bu":2407857.1,"avg_val_sd":2003578.6,"acum_busd":13500,"acum_busd_val":16200000,"acum_val_bu":16200000,"acum_val_sd":0,"rbusd":1.2},{"c":1.2,"h":1.2,"l":1.2,"o":1.2,"bu":300,"val_bu":360000,"total_vol":13800,"sum_vol":300,"val":360000,"acum_val":16560000,"datetime":1671183300000,"date":"2022-12-16T09:35:00.000Z","pbu":100,"psd":0,"puk":0,"bs":null,"sb":0,"abu":2078.6,"asd":1828.6,"auk":0,"rbu":0.1,"bu-sd":300,"bu-sd_val":360000,"avg_val_bu":2407857.1,"avg_val_sd":2003578.6,"acum_busd":13800,"acum_busd_val":16560000,"acum_val_bu":16560000,"acum_val_sd":0,"rbusd":0.9},{"c":1.2,"h":1.2,"l":1.2,"o":1.2,"bu":1400,"val_bu":1680000,"total_vol":15200,"sum_vol":1400,"val":1680000,"acum_val":18240000,"datetime":1671183900000,"date":"2022-12-16T09:45:00.000Z","pbu":100,"psd":0,"puk":0,"bs":null,"sb":0,"abu":2078.6,"asd":1828.6,"auk":0,"rbu":0.7,"bu-sd":1400,"bu-sd_val":1680000,"avg_val_bu":2407857.1,"avg_val_sd":2003578.6,"acum_busd":15200,"acum_busd_val":18240000,"acum_val_bu":18240000,"acum_val_sd":0,"rbusd":4.2},{"c":1.2,"h":1.2,"l":1.2,"o":1.2,"bu":500,"val_bu":600000,"total_vol":15700,"sum_vol":500,"val":600000,"acum_val":18840000,"datetime":1671185400000,"date":"2022-12-16T10:10:00.000Z","pbu":100,"psd":0,"puk":0,"bs":null,"sb":0,"abu":2078.6,"asd":1828.6,"auk":0,"rbu":0.2,"bu-sd":500,"bu-sd_val":600000,"avg_val_bu":2407857.1,"avg_val_sd":2003578.6,"acum_busd":15700,"acum_busd_val":18840000,"acum_val_bu":18840000,"acum_val_sd":0,"rbusd":1.5},{"c":1.2,"h":1.2,"l":1.2,"o":1.2,"bu":600,"val_bu":720000,"total_vol":16300,"sum_vol":600,"val":720000,"acum_val":19560000,"datetime":1671186000000,"date":"2022-12-16T10:20:00.000Z","pbu":100,"psd":0,"puk":0,"bs":null,"sb":0,"abu":2078.6,"asd":1828.6,"auk":0,"rbu":0.3,"bu-sd":600,"bu-sd_val":720000,"avg_val_bu":2407857.1,"avg_val_sd":2003578.6,"acum_busd":16300,"acum_busd_val":19560000,"acum_val_bu":19560000,"acum_val_sd":0,"rbusd":1.8},{"c":1.1,"h":1.2,"l":1.1,"o":1.2,"bu":700,"val_bu":840000,"total_vol":24000,"sum_vol":7700,"val":8540000,"acum_val":28100000,"sd":7000,"val_sd":7700000.000000001,"datetime":1671186600000,"date":"2022-12-16T10:30:00.000Z","pbu":9.1,"psd":90.9,"puk":0,"bs":0.1,"sb":10,"abu":2078.6,"asd":1828.6,"auk":0,"rsd":3.8,"rbu":0.3,"bu-sd":-6300,"bu-sd_val":-6860000.000000001,"avg_val_bu":2407857.1,"avg_val_sd":2003578.6,"acum_busd":10000,"acum_busd_val":12700000,"acum_val_bu":20400000,"acum_val_sd":7700000.000000001,"rbusd":-17},{"c":1.1,"h":1.1,"l":1.1,"o":1.1,"sd":8100,"val_sd":8910000,"total_vol":32100,"sum_vol":8100,"val":8910000,"acum_val":37010000,"datetime":1671186900000,"date":"2022-12-16T10:35:00.000Z","pbu":0,"psd":100,"puk":0,"bs":0,"sb":null,"abu":2078.6,"asd":1828.6,"auk":0,"rsd":4.4,"bu-sd":-8100,"bu-sd_val":-8910000,"avg_val_bu":2407857.1,"avg_val_sd":2003578.6,"acum_busd":1900,"acum_busd_val":3790000,"acum_val_bu":20400000,"acum_val_sd":16610000,"rbusd":-22},{"c":1.1,"h":1.1,"l":1.1,"o":1.1,"sd":5000,"val_sd":5500000,"total_vol":37100,"sum_vol":5000,"val":5500000,"acum_val":42510000,"datetime":1671187500000,"date":"2022-12-16T10:45:00.000Z","pbu":0,"psd":100,"puk":0,"bs":0,"sb":null,"abu":2078.6,"asd":1828.6,"auk":0,"rsd":2.7,"bu-sd":-5000,"bu-sd_val":-5500000,"avg_val_bu":2407857.1,"avg_val_sd":2003578.6,"acum_busd":-3100,"acum_busd_val":-1710000,"acum_val_bu":20400000,"acum_val_sd":22110000,"rbusd":-13.6},{"c":1.1,"h":1.1,"l":1.1,"o":1.1,"bu":200,"val_bu":220000.00000000003,"total_vol":37300,"sum_vol":200,"val":220000.00000000003,"acum_val":42730000,"datetime":1671188100000,"date":"2022-12-16T10:55:00.000Z","pbu":100,"psd":0,"puk":0,"bs":null,"sb":0,"abu":2078.6,"asd":1828.6,"auk":0,"rbu":0.1,"bu-sd":200,"bu-sd_val":220000.00000000003,"avg_val_bu":2407857.1,"avg_val_sd":2003578.6,"acum_busd":-2900,"acum_busd_val":-1490000,"acum_val_bu":20620000,"acum_val_sd":22110000,"rbusd":0.5},{"c":1.1,"h":1.1,"l":1.1,"o":1.1,"bu":1900,"val_bu":2090000,"total_vol":39200,"sum_vol":1900,"val":2090000,"acum_val":44820000,"datetime":1671189000000,"date":"2022-12-16T11:10:00.000Z","pbu":100,"psd":0,"puk":0,"bs":null,"sb":0,"abu":2078.6,"asd":1828.6,"auk":0,"rbu":0.9,"bu-sd":1900,"bu-sd_val":2090000,"avg_val_bu":2407857.1,"avg_val_sd":2003578.6,"acum_busd":-1000,"acum_busd_val":600000,"acum_val_bu":22710000,"acum_val_sd":22110000,"rbusd":5.2},{"c":1.1,"h":1.1,"l":1.1,"o":1.1,"sd":5400,"val_sd":5940000.000000001,"total_vol":44600,"sum_vol":5400,"val":5940000.000000001,"acum_val":50760000,"datetime":1671197100000,"date":"2022-12-16T13:25:00.000Z","pbu":0,"psd":100,"puk":0,"bs":0,"sb":null,"abu":2078.6,"asd":1828.6,"auk":0,"rsd":3,"bu-sd":-5400,"bu-sd_val":-5940000.000000001,"avg_val_bu":2407857.1,"avg_val_sd":2003578.6,"acum_busd":-6400,"acum_busd_val":-5340000.000000001,"acum_val_bu":22710000,"acum_val_sd":28050000,"rbusd":-14.7},{"c":1.1,"h":1.1,"l":1.1,"o":1.1,"bu":10000,"val_bu":11000000,"total_vol":54600,"sum_vol":10000,"val":11000000,"acum_val":61760000,"datetime":1671197700000,"date":"2022-12-16T13:35:00.000Z","pbu":100,"psd":0,"puk":0,"bs":null,"sb":0,"abu":2078.6,"asd":1828.6,"auk":0,"rbu":4.8,"bu-sd":10000,"bu-sd_val":11000000,"avg_val_bu":2407857.1,"avg_val_sd":2003578.6,"acum_busd":3600,"acum_busd_val":5659999.999999999,"acum_val_bu":33710000,"acum_val_sd":28050000,"rbusd":27.2},{"c":1,"h":1,"l":1,"o":1,"sd":100,"val_sd":100,"total_vol":54700,"sum_vol":100,"val":100,"acum_val":61760100,"datetime":1671202800000,"date":"2022-12-16T15:00:00.000Z","pbu":0,"psd":100,"puk":0,"bs":0,"sb":null,"abu":2078.6,"asd":1828.6,"auk":0,"rsd":0.1,"bu-sd":-100,"bu-sd_val":-100,"avg_val_bu":2407857.1,"avg_val_sd":2003578.6,"acum_busd":3500,"acum_busd_val":5659899.999999999,"acum_val_bu":33710000,"acum_val_sd":28050100,"rbusd":0}]
[{"c":1.1,"h":1.1,"l":1.1,"o":1.1,"sd":30700,"val_sd":33770000,"total_vol":30700,"sum_vol":30700,"val":33770000,"acum_val":33770000,"datetime":1670576400000,"date":"2022-12-09T09:00:00.000Z","pbu":0,"psd":100,"puk":0,"bs":0,"sb":null,"abu":0,"asd":13088.9,"auk":0,"rsd":2.3,"bu-sd":-30700,"bu-sd_val":-33770000,"avg_val_bu":0,"avg_val_sd":14397777.8,"acum_busd":-30700,"acum_busd_val":-33770000,"acum_val_bu":0,"acum_val_sd":33770000,"rbusd":2.3},{"c":1.1,"h":1.1,"l":1.1,"o":1.1,"sd":7800,"val_sd":8580000.000000002,"total_vol":38500,"sum_vol":7800,"val":8580000.000000002,"acum_val":42350000,"datetime":1670577900000,"date":"2022-12-09T09:25:00.000Z","pbu":0,"psd":100,"puk":0,"bs":0,"sb":null,"abu":0,"asd":13088.9,"auk":0,"rsd":0.6,"bu-sd":-7800,"bu-sd_val":-8580000.000000002,"avg_val_bu":0,"avg_val_sd":14397777.8,"acum_busd":-38500,"acum_busd_val":-42350000,"acum_val_bu":0,"acum_val_sd":42350000,"rbusd":0.6},{"c":1.1,"h":1.1,"l":1.1,"o":1.1,"sd":1000,"val_sd":1100000,"total_vol":39500,"sum_vol":1000,"val":1100000,"acum_val":43450000,"datetime":1670578200000,"date":"2022-12-09T09:30:00.000Z","pbu":0,"psd":100,"puk":0,"bs":0,"sb":null,"abu":0,"asd":13088.9,"auk":0,"rsd":0.1,"bu-sd":-1000,"bu-sd_val":-1100000,"avg_val_bu":0,"avg_val_sd":14397777.8,"acum_busd":-39500,"acum_busd_val":-43450000,"acum_val_bu":0,"acum_val_sd":43450000,"rbusd":0.1},{"c":1.1,"h":1.1,"l":1.1,"o":1.1,"sd":3600,"val_sd":3960000.0000000005,"total_vol":43100,"sum_vol":3600,"val":3960000.0000000005,"acum_val":47410000,"datetime":1670578800000,"date":"2022-12-09T09:40:00.000Z","pbu":0,"psd":100,"puk":0,"bs":0,"sb":null,"abu":0,"asd":13088.9,"auk":0,"rsd":0.3,"bu-sd":-3600,"bu-sd_val":-3960000.0000000005,"avg_val_bu":0,"avg_val_sd":14397777.8,"acum_busd":-43100,"acum_busd_val":-47410000,"acum_val_bu":0,"acum_val_sd":47410000,"rbusd":0.3},{"c":1.1,"h":1.1,"l":1.1,"o":1.1,"sd":25100,"val_sd":27610000.000000004,"total_vol":68200,"sum_vol":25100,"val":27610000.000000004,"acum_val":75020000,"datetime":1670580000000,"date":"2022-12-09T10:00:00.000Z","pbu":0,"psd":100,"puk":0,"bs":0,"sb":null,"abu":0,"asd":13088.9,"auk":0,"rsd":1.9,"bu-sd":-25100,"bu-sd_val":-27610000.000000004,"avg_val_bu":0,"avg_val_sd":14397777.8,"acum_busd":-68200,"acum_busd_val":-75020000,"acum_val_bu":0,"acum_val_sd":75020000,"rbusd":1.9},{"c":1.1,"h":1.1,"l":1.1,"o":1.1,"sd":3000,"val_sd":3300000.0000000005,"total_vol":71200,"sum_vol":3000,"val":3300000.0000000005,"acum_val":78320000,"datetime":1670580300000,"date":"2022-12-09T10:05:00.000Z","pbu":0,"psd":100,"puk":0,"bs":0,"sb":null,"abu":0,"asd":13088.9,"auk":0,"rsd":0.2,"bu-sd":-3000,"bu-sd_val":-3300000.0000000005,"avg_val_bu":0,"avg_val_sd":14397777.8,"acum_busd":-71200,"acum_busd_val":-78320000,"acum_val_bu":0,"acum_val_sd":78320000,"rbusd":0.2},{"c":1.1,"h":1.1,"l":1.1,"o":1.1,"sd":4500,"val_sd":4950000,"total_vol":75700,"sum_vol":4500,"val":4950000,"acum_val":83270000,"datetime":1670580600000,"date":"2022-12-09T10:10:00.000Z","pbu":0,"psd":100,"puk":0,"bs":0,"sb":null,"abu":0,"asd":13088.9,"auk":0,"rsd":0.3,"bu-sd":-4500,"bu-sd_val":-4950000,"avg_val_bu":0,"avg_val_sd":14397777.8,"acum_busd":-75700,"acum_busd_val":-83270000,"acum_val_bu":0,"acum_val_sd":83270000,"rbusd":0.3},{"c":1.1,"h":1.1,"l":1.1,"o":1.1,"sd":24700,"val_sd":27170000.000000004,"total_vol":100400,"sum_vol":24700,"val":27170000.000000004,"acum_val":110440000,"datetime":1670583000000,"date":"2022-12-09T10:50:00.000Z","pbu":0,"psd":100,"puk":0,"bs":0,"sb":null,"abu":0,"asd":13088.9,"auk":0,"rsd":1.9,"bu-sd":-24700,"bu-sd_val":-27170000.000000004,"avg_val_bu":0,"avg_val_sd":14397777.8,"acum_busd":-100400,"acum_busd_val":-110440000,"acum_val_bu":0,"acum_val_sd":110440000,"rbusd":1.9},{"c":1.1,"h":1.1,"l":1.1,"o":1.1,"sd":17400,"val_sd":19140000,"total_vol":117800,"sum_vol":17400,"val":19140000,"acum_val":129580000,"datetime":1670584800000,"date":"2022-12-09T11:20:00.000Z","pbu":0,"psd":100,"puk":0,"bs":0,"sb":null,"abu":0,"asd":13088.9,"auk":0,"rsd":1.3,"bu-sd":-17400,"bu-sd_val":-19140000,"avg_val_bu":0,"avg_val_sd":14397777.8,"acum_busd":-117800,"acum_busd_val":-129580000,"acum_val_bu":0,"acum_val_sd":129580000,"rbusd":1.3}]
