[{"c":12.5,"h":12.5,"l":12.5,"o":12.5,"uk":3000,"val_uk":37500000,"total_vol":3000,"sum_vol":3000,"val":37500000,"acum_val":40080000,"datetime":1670406960000,"date":"2022-12-07T09:56:00.000Z","pbu":0,"psd":0,"puk":100,"bs":null,"sb":null,"abu":480,"asd":220,"auk":1920,"ruk":1.6,"bu-sd":0,"bu-sd_val":0,"avg_val_bu":5952000,"avg_val_sd":250400,"acum_busd":0,"acum_busd_val":0,"acum_val_bu":0,"acum_val_sd":0,"rbusd":0},{"c":12.4,"h":12.4,"l":12.4,"o":12.4,"uk":2000,"val_uk":24800000,"total_vol":5000,"sum_vol":2000,"val":24800000,"acum_val":64880000,"datetime":1670407080000,"date":"2022-12-07T09:58:00.000Z","pbu":0,"psd":0,"puk":100,"bs":null,"sb":null,"abu":480,"asd":220,"auk":1920,"ruk":1,"bu-sd":0,"bu-sd_val":0,"avg_val_bu":5952000,"avg_val_sd":250400,"acum_busd":0,"acum_busd_val":0,"acum_val_bu":0,"acum_val_sd":0,"rbusd":0},{"c":12,"h":12.4,"l":12,"o":12.4,"sd":200,"val_sd":2480000,"total_vol":12200,"sum_vol":7200,"val":51716000,"acum_val":116596000,"uk":7000,"val_uk":49236000,"datetime":1670409240000,"date":"2022-12-07T10:34:00.000Z","pbu":0,"psd":2.8,"puk":97.2,"bs":0,"sb":null,"abu":480,"asd":220,"auk":1920,"ruk":3.6,"rsd":0.9,"bu-sd":-200,"bu-sd_val":-2480000,"avg_val_bu":5952000,"avg_val_sd":250400,"acum_busd":-200,"acum_busd_val":-2480000,"acum_val_bu":0,"acum_val_sd":2480000,"rbusd":0.4},{"c":11.9,"h":11.9,"l":11.9,"o":11.9,"uk":3000,"val_uk":35700000,"total_vol":15200,"sum_vol":3000,"val":35700000,"acum_val":152296000,"datetime":1670409960000,"date":"2022-12-07T10:46:00.000Z","pbu":0,"psd":0,"puk":100,"bs":null,"sb":null,"abu":480,"asd":220,"auk":1920,"ruk":1.6,"bu-sd":0,"bu-sd_val":0,"avg_val_bu":5952000,"avg_val_sd":250400,"acum_busd":-200,"acum_busd_val":-2480000,"acum_val_bu":0,"acum_val_sd":2480000,"rbusd":0},{"c":12.9,"h":12.9,"l":12.9,"o":12.9,"uk":200,"val_uk":2580000,"total_vol":100,"sum_vol":200,"val":2580000,"acum_val":2580000,"datetime":1670410800000,"date":"2022-12-07T11:00:00.000Z","pbu":0,"psd":0,"puk":100,"bs":null,"sb":null,"abu":480,"asd":220,"auk":1920,"ruk":0.1,"bu-sd":0,"bu-sd_val":0,"avg_val_bu":5952000,"avg_val_sd":250400,"acum_busd":-200,"acum_busd_val":-2480000,"acum_val_bu":0,"acum_val_sd":2480000,"rbusd":0},{"c":12.4,"h":12.4,"l":12.4,"o":12.4,"bu":3000,"val_bu":37200000,"total_vol":18200,"sum_vol":3000,"val":37200000,"acum_val":189496000,"datetime":1670412360000,"date":"2022-12-07T11:26:00.000Z","pbu":100,"psd":0,"puk":0,"bs":null,"sb":0,"abu":480,"asd":220,"auk":1920,"rbu":6.3,"bu-sd":3000,"bu-sd_val":37200000,"avg_val_bu":5952000,"avg_val_sd":250400,"acum_busd":2800,"acum_busd_val":34720000,"acum_val_bu":37200000,"acum_val_sd":2480000,"rbusd":6.5},{"c":12,"h":12,"l":12,"o":12,"uk":2000,"val_uk":24000,"total_vol":20200,"sum_vol":2000,"val":24000,"acum_val":189520000,"datetime":1670412480000,"date":"2022-12-07T11:28:00.000Z","pbu":0,"psd":0,"puk":100,"bs":null,"sb":null,"abu":480,"asd":220,"auk":1920,"ruk":1,"bu-sd":0,"bu-sd_val":0,"avg_val_bu":5952000,"avg_val_sd":250400,"acum_busd":2800,"acum_busd_val":34720000,"acum_val_bu":37200000,"acum_val_sd":2480000,"rbusd":0},{"c":12.4,"h":12.4,"l":12.4,"o":12.4,"bu":1800,"val_bu":22320000,"total_vol":22000,"sum_vol":1800,"val":22320000,"acum_val":211840000,"datetime":1670418600000,"date":"2022-12-07T13:10:00.000Z","pbu":100,"psd":0,"puk":0,"bs":null,"sb":0,"abu":480,"asd":220,"auk":1920,"rbu":3.8,"bu-sd":1800,"bu-sd_val":22320000,"avg_val_bu":5952000,"avg_val_sd":250400,"acum_busd":4600,"acum_busd_val":57040000,"acum_val_bu":59520000,"acum_val_sd":2480000,"rbusd":3.9},{"c":12,"h":12,"l":12,"o":12,"uk":2000,"val_uk":24000,"total_vol":24000,"sum_vol":2000,"val":24000,"acum_val":211864000,"datetime":1670422080000,"date":"2022-12-07T14:08:00.000Z","pbu":0,"psd":0,"puk":100,"bs":null,"sb":null,"abu":480,"asd":220,"auk":1920,"ruk":1,"bu-sd":0,"bu-sd_val":0,"avg_val_bu":5952000,"avg_val_sd":250400,"acum_busd":4600,"acum_busd_val":57040000,"acum_val_bu":59520000,"acum_val_sd":2480000,"rbusd":0},{"c":12,"h":12,"l":12,"o":12,"sd":2000,"val_sd":24000,"total_vol":26000,"sum_vol":2000,"val":24000,"acum_val":211888000,"datetime":1670423280000,"date":"2022-12-07T14:28:00.000Z","pbu":0,"psd":100,"puk":0,"bs":0,"sb":null,"abu":480,"asd":220,"auk":1920,"rsd":9.1,"bu-sd":-2000,"bu-sd_val":-24000,"avg_val_bu":5952000,"avg_val_sd":250400,"acum_busd":2600,"acum_busd_val":57016000,"acum_val_bu":59520000,"acum_val_sd":2504000,"rbusd":0}]