[{"c":13.2,"h":13.2,"l":13.2,"o":13.2,"sd":400,"val_sd":5280000,"total_vol":400,"sum_vol":400,"val":5280000,"acum_val":5280000,"datetime":1672304760000,"date":"2022-12-29T09:06:00.000Z","pbu":0,"psd":100,"puk":0,"bs":0,"sb":null,"abu":137.5,"asd":112.5,"auk":62.5,"rsd":3.6,"bu-sd":-400,"bu-sd_val":-5280000,"avg_val_bu":1815000,"avg_val_sd":1478750,"acum_busd":-400,"acum_busd_val":-5280000,"acum_val_bu":0,"acum_val_sd":5280000,"rbusd":15.7},{"c":13.2,"h":13.2,"l":13.2,"o":13.2,"bu":800,"val_bu":10560000,"total_vol":1200,"sum_vol":800,"val":10560000,"acum_val":15840000,"datetime":1672305360000,"date":"2022-12-29T09:16:00.000Z","pbu":100,"psd":0,"puk":0,"bs":null,"sb":0,"abu":137.5,"asd":112.5,"auk":62.5,"rbu":5.8,"bu-sd":800,"bu-sd_val":10560000,"avg_val_bu":1815000,"avg_val_sd":1478750,"acum_busd":400,"acum_busd_val":5280000,"acum_val_bu":10560000,"acum_val_sd":5280000,"rbusd":31.4},{"c":13.2,"h":13.2,"l":13.2,"o":13.2,"bu":100,"val_bu":1320000,"total_vol":1300,"sum_vol":100,"val":1320000,"acum_val":17160000,"datetime":1672306560000,"date":"2022-12-29T09:36:00.000Z","pbu":100,"psd":0,"puk":0,"bs":null,"sb":0,"abu":137.5,"asd":112.5,"auk":62.5,"rbu":0.7,"bu-sd":100,"bu-sd_val":1320000,"avg_val_bu":1815000,"avg_val_sd":1478750,"acum_busd":500,"acum_busd_val":6600000,"acum_val_bu":11880000,"acum_val_sd":5280000,"rbusd":3.9},{"c":13.2,"h":13.2,"l":13.2,"o":13.2,"bu":200,"val_bu":2640000,"total_vol":1500,"sum_vol":200,"val":2640000,"acum_val":19800000,"datetime":1672308360000,"date":"2022-12-29T10:06:00.000Z","pbu":100,"psd":0,"puk":0,"bs":null,"sb":0,"abu":137.5,"asd":112.5,"auk":62.5,"rbu":1.5,"bu-sd":200,"bu-sd_val":2640000,"avg_val_bu":1815000,"avg_val_sd":1478750,"acum_busd":700,"acum_busd_val":9240000,"acum_val_bu":14520000,"acum_val_sd":5280000,"rbusd":7.9},{"c":13.1,"h":13.1,"l":13.1,"o":13.1,"uk":400,"val_uk":5240000,"total_vol":1900,"sum_vol":400,"val":5240000,"acum_val":25040000,"datetime":1672309560000,"date":"2022-12-29T10:26:00.000Z","pbu":0,"psd":0,"puk":100,"bs":null,"sb":null,"abu":137.5,"asd":112.5,"auk":62.5,"ruk":6.4,"bu-sd":0,"bu-sd_val":0,"avg_val_bu":1815000,"avg_val_sd":1478750,"acum_busd":700,"acum_busd_val":9240000,"acum_val_bu":14520000,"acum_val_sd":5280000,"rbusd":0},{"c":13.1,"h":13.1,"l":13.1,"o":13.1,"sd":200,"val_sd":2620000,"total_vol":2100,"sum_vol":200,"val":2620000,"acum_val":27660000,"datetime":1672320720000,"date":"2022-12-29T13:32:00.000Z","pbu":0,"psd":100,"puk":0,"bs":0,"sb":null,"abu":137.5,"asd":112.5,"auk":62.5,"rsd":1.8,"bu-sd":-200,"bu-sd_val":-2620000,"avg_val_bu":1815000,"avg_val_sd":1478750,"acum_busd":500,"acum_busd_val":6620000,"acum_val_bu":14520000,"acum_val_sd":7900000,"rbusd":7.8},{"c":13.1,"h":13.1,"l":13.1,"o":13.1,"sd":300,"val_sd":3930000,"total_vol":2400,"sum_vol":300,"val":3930000,"acum_val":31590000,"datetime":1672323120000,"date":"2022-12-29T14:12:00.000Z","pbu":0,"psd":100,"puk":0,"bs":0,"sb":null,"abu":137.5,"asd":112.5,"auk":62.5,"rsd":2.7,"bu-sd":-300,"bu-sd_val":-3930000,"avg_val_bu":1815000,"avg_val_sd":1478750,"acum_busd":200,"acum_busd_val":2690000,"acum_val_bu":14520000,"acum_val_sd":11830000,"rbusd":11.7},{"c":13.1,"h":13.1,"l":13.1,"o":13.1,"uk":100,"val_uk":1310000,"total_vol":2500,"sum_vol":100,"val":1310000,"acum_val":32900000,"datetime":1672323240000,"date":"2022-12-29T14:14:00.000Z","pbu":0,"psd":0,"puk":100,"bs":null,"sb":null,"abu":137.5,"asd":112.5,"auk":62.5,"ruk":1.6,"bu-sd":0,"bu-sd_val":0,"avg_val_bu":1815000,"avg_val_sd":1478750,"acum_busd":200,"acum_busd_val":2690000,"acum_val_bu":14520000,"acum_val_sd":11830000,"rbusd":0}]