[{"c":2800,"h":2800,"l":2800,"o":2800,"sd":200,"val_sd":560000,"total_vol":200,"sum_vol":200,"val":560000,"acum_val":560000,"datetime":1676625360000,"date":"2023-02-17T09:16:00.000Z","pbu":0,"psd":100,"puk":0,"bs":0,"sb":null,"abu":646.2,"asd":880.8,"auk":15.4,"rsd":0.2,"bu-sd":-200,"bu-sd_val":-560000,"avg_val_bu":1946153.8,"avg_val_sd":2564230.8,"acum_busd":-200,"acum_busd_val":-560000,"acum_val_bu":0,"acum_val_sd":560000,"rbusd":0.9},{"c":3000,"h":3000,"l":3000,"o":3000,"uk":200,"val_uk":600000,"total_vol":400,"sum_vol":200,"val":600000,"acum_val":1160000,"datetime":1676626200000,"date":"2023-02-17T09:30:00.000Z","pbu":0,"psd":0,"puk":100,"bs":null,"sb":null,"abu":646.2,"asd":880.8,"auk":15.4,"ruk":13,"bu-sd":0,"bu-sd_val":0,"avg_val_bu":1946153.8,"avg_val_sd":2564230.8,"acum_busd":-200,"acum_busd_val":-560000,"acum_val_bu":0,"acum_val_sd":560000,"rbusd":0},{"c":3000,"h":3000,"l":3000,"o":3000,"bu":200,"val_bu":600000,"total_vol":600,"sum_vol":200,"val":600000,"acum_val":1760000,"datetime":1676626440000,"date":"2023-02-17T09:34:00.000Z","pbu":100,"psd":0,"puk":0,"bs":null,"sb":0,"abu":646.2,"asd":880.8,"auk":15.4,"rbu":0.3,"bu-sd":200,"bu-sd_val":600000,"avg_val_bu":1946153.8,"avg_val_sd":2564230.8,"acum_busd":0,"acum_busd_val":40000,"acum_val_bu":600000,"acum_val_sd":560000,"rbusd":-1},{"c":3000,"h":3000,"l":3000,"o":3000,"bu":300,"val_bu":900000,"total_vol":1100,"sum_vol":500,"val":1500000,"acum_val":3260000,"uk":200,"val_uk":600000,"datetime":1676626680000,"date":"2023-02-17T09:38:00.000Z","pbu":60,"psd":0,"puk":40,"bs":null,"sb":0,"abu":646.2,"asd":880.8,"auk":15.4,"ruk":13,"rbu":0.5,"bu-sd":300,"bu-sd_val":900000,"avg_val_bu":1946153.8,"avg_val_sd":2564230.8,"acum_busd":300,"acum_busd_val":940000,"acum_val_bu":1500000,"acum_val_sd":560000,"rbusd":-1.5},{"c":3000,"h":3000,"l":3000,"o":3000,"bu":5000,"val_bu":15000000,"total_vol":6100,"sum_vol":5000,"val":15000000,"acum_val":18260000,"datetime":1676626800000,"date":"2023-02-17T09:40:00.000Z","pbu":100,"psd":0,"puk":0,"bs":null,"sb":0,"abu":646.2,"asd":880.8,"auk":15.4,"rbu":7.7,"bu-sd":5000,"bu-sd_val":15000000,"avg_val_bu":1946153.8,"avg_val_sd":2564230.8,"acum_busd":5300,"acum_busd_val":15940000,"acum_val_bu":16500000,"acum_val_sd":560000,"rbusd":-24.3},{"c":3000,"h":3000,"l":3000,"o":3000,"bu":400,"val_bu":1200000,"total_vol":6500,"sum_vol":400,"val":1200000,"acum_val":19460000,"datetime":1676626920000,"date":"2023-02-17T09:42:00.000Z","pbu":100,"psd":0,"puk":0,"bs":null,"sb":0,"abu":646.2,"asd":880.8,"auk":15.4,"rbu":0.6,"bu-sd":400,"bu-sd_val":1200000,"avg_val_bu":1946153.8,"avg_val_sd":2564230.8,"acum_busd":5700,"acum_busd_val":17140000,"acum_val_bu":17700000,"acum_val_sd":560000,"rbusd":-1.9},{"c":3000,"h":3000,"l":3000,"o":3000,"bu":100,"val_bu":300000,"total_vol":6600,"sum_vol":100,"val":300000,"acum_val":19760000,"datetime":1676628600000,"date":"2023-02-17T10:10:00.000Z","pbu":100,"psd":0,"puk":0,"bs":null,"sb":0,"abu":646.2,"asd":880.8,"auk":15.4,"rbu":0.2,"bu-sd":100,"bu-sd_val":300000,"avg_val_bu":1946153.8,"avg_val_sd":2564230.8,"acum_busd":5800,"acum_busd_val":17440000,"acum_val_bu":18000000,"acum_val_sd":560000,"rbusd":-0.5},{"c":2900,"h":2900,"l":2900,"o":2900,"sd":100,"val_sd":290000,"total_vol":6700,"sum_vol":100,"val":290000,"acum_val":20050000,"datetime":1676628840000,"date":"2023-02-17T10:14:00.000Z","pbu":0,"psd":100,"puk":0,"bs":0,"sb":null,"abu":646.2,"asd":880.8,"auk":15.4,"rsd":0.1,"bu-sd":-100,"bu-sd_val":-290000,"avg_val_bu":1946153.8,"avg_val_sd":2564230.8,"acum_busd":5700,"acum_busd_val":17150000,"acum_val_bu":18000000,"acum_val_sd":850000,"rbusd":0.5},{"c":3000,"h":3000,"l":3000,"o":3000,"sd":2800,"val_sd":8400000,"total_vol":10700,"sum_vol":4000,"val":12000000,"acum_val":32050000,"bu":1200,"val_bu":3600000,"datetime":1676629920000,"date":"2023-02-17T10:32:00.000Z","pbu":30,"psd":70,"puk":0,"bs":0.4,"sb":2.3,"abu":646.2,"asd":880.8,"auk":15.4,"rsd":3.2,"rbu":1.9,"bu-sd":-1600,"bu-sd_val":-4800000,"avg_val_bu":1946153.8,"avg_val_sd":2564230.8,"acum_busd":4100,"acum_busd_val":12350000,"acum_val_bu":21600000,"acum_val_sd":9250000,"rbusd":7.8},{"c":3000,"h":3000,"l":3000,"o":3000,"bu":200,"val_bu":600000,"total_vol":10900,"sum_vol":200,"val":600000,"acum_val":32650000,"datetime":1676631120000,"date":"2023-02-17T10:52:00.000Z","pbu":100,"psd":0,"puk":0,"bs":null,"sb":0,"abu":646.2,"asd":880.8,"auk":15.4,"rbu":0.3,"bu-sd":200,"bu-sd_val":600000,"avg_val_bu":1946153.8,"avg_val_sd":2564230.8,"acum_busd":4300,"acum_busd_val":12950000,"acum_val_bu":22200000,"acum_val_sd":9250000,"rbusd":-1},{"c":2900,"h":2900,"l":2900,"o":2900,"sd":5000,"val_sd":14500000,"total_vol":15900,"sum_vol":5000,"val":14500000,"acum_val":47150000,"datetime":1676632080000,"date":"2023-02-17T11:08:00.000Z","pbu":0,"psd":100,"puk":0,"bs":0,"sb":null,"abu":646.2,"asd":880.8,"auk":15.4,"rsd":5.7,"bu-sd":-5000,"bu-sd_val":-14500000,"avg_val_bu":1946153.8,"avg_val_sd":2564230.8,"acum_busd":-700,"acum_busd_val":-1550000,"acum_val_bu":22200000,"acum_val_sd":23750000,"rbusd":23.5},{"c":2900,"h":2900,"l":2900,"o":2900,"sd":100,"val_sd":290000,"total_vol":16000,"sum_vol":100,"val":290000,"acum_val":47440000,"datetime":1676638800000,"date":"2023-02-17T13:00:00.000Z","pbu":0,"psd":100,"puk":0,"bs":0,"sb":null,"abu":646.2,"asd":880.8,"auk":15.4,"rsd":0.1,"bu-sd":-100,"bu-sd_val":-290000,"avg_val_bu":1946153.8,"avg_val_sd":2564230.8,"acum_busd":-800,"acum_busd_val":-1840000,"acum_val_bu":22200000,"acum_val_sd":24040000,"rbusd":0.5},{"c":3000,"h":3000,"l":3000,"o":3000,"bu":100,"val_bu":300000,"total_vol":16100,"sum_vol":100,"val":300000,"acum_val":47740000,"datetime":1676640000000,"date":"2023-02-17T13:20:00.000Z","pbu":100,"psd":0,"puk":0,"bs":null,"sb":0,"abu":646.2,"asd":880.8,"auk":15.4,"rbu":0.2,"bu-sd":100,"bu-sd_val":300000,"avg_val_bu":1946153.8,"avg_val_sd":2564230.8,"acum_busd":-700,"acum_busd_val":-1540000,"acum_val_bu":22500000,"acum_val_sd":24040000,"rbusd":-0.5},{"c":3000,"h":3000,"l":3000,"o":3000,"bu":100,"val_bu":300000,"total_vol":16200,"sum_vol":100,"val":300000,"acum_val":48040000,"datetime":1676640120000,"date":"2023-02-17T13:22:00.000Z","pbu":100,"psd":0,"puk":0,"bs":null,"sb":0,"abu":646.2,"asd":880.8,"auk":15.4,"rbu":0.2,"bu-sd":100,"bu-sd_val":300000,"avg_val_bu":1946153.8,"avg_val_sd":2564230.8,"acum_busd":-600,"acum_busd_val":-1240000,"acum_val_bu":22800000,"acum_val_sd":24040000,"rbusd":-0.5},{"c":2900,"h":2900,"l":2900,"o":2900,"sd":2000,"val_sd":5800000,"total_vol":18200,"sum_vol":2000,"val":5800000,"acum_val":53840000,"datetime":1676640240000,"date":"2023-02-17T13:24:00.000Z","pbu":0,"psd":100,"puk":0,"bs":0,"sb":null,"abu":646.2,"asd":880.8,"auk":15.4,"rsd":2.3,"bu-sd":-2000,"bu-sd_val":-5800000,"avg_val_bu":1946153.8,"avg_val_sd":2564230.8,"acum_busd":-2600,"acum_busd_val":-7040000,"acum_val_bu":22800000,"acum_val_sd":29840000,"rbusd":9.4},{"c":2900,"h":3000,"l":2900,"o":3000,"bu":100,"val_bu":300000,"total_vol":21300,"sum_vol":3100,"val":9000000,"acum_val":62840000,"sd":3000,"val_sd":8700000,"datetime":1676641200000,"date":"2023-02-17T13:40:00.000Z","pbu":3.2,"psd":96.8,"puk":0,"bs":0,"sb":30,"abu":646.2,"asd":880.8,"auk":15.4,"rsd":3.4,"rbu":0.2,"bu-sd":-2900,"bu-sd_val":-8400000,"avg_val_bu":1946153.8,"avg_val_sd":2564230.8,"acum_busd":-5500,"acum_busd_val":-15440000,"acum_val_bu":23100000,"acum_val_sd":38540000,"rbusd":13.6},{"c":3000,"h":3000,"l":3000,"o":3000,"bu":2200,"val_bu":6600000,"total_vol":23500,"sum_vol":2200,"val":6600000,"acum_val":69440000,"datetime":1676641320000,"date":"2023-02-17T13:42:00.000Z","pbu":100,"psd":0,"puk":0,"bs":null,"sb":0,"abu":646.2,"asd":880.8,"auk":15.4,"rbu":3.4,"bu-sd":2200,"bu-sd_val":6600000,"avg_val_bu":1946153.8,"avg_val_sd":2564230.8,"acum_busd":-3300,"acum_busd_val":-8840000,"acum_val_bu":29700000,"acum_val_sd":38540000,"rbusd":-10.7},{"c":3000,"h":3000,"l":3000,"o":3000,"bu":500,"val_bu":1500000,"total_vol":24000,"sum_vol":500,"val":1500000,"acum_val":70940000,"datetime":1676641440000,"date":"2023-02-17T13:44:00.000Z","pbu":100,"psd":0,"puk":0,"bs":null,"sb":0,"abu":646.2,"asd":880.8,"auk":15.4,"rbu":0.8,"bu-sd":500,"bu-sd_val":1500000,"avg_val_bu":1946153.8,"avg_val_sd":2564230.8,"acum_busd":-2800,"acum_busd_val":-7340000,"acum_val_bu":31200000,"acum_val_sd":38540000,"rbusd":-2.4},{"c":3100,"h":3100,"l":3100,"o":3100,"bu":2000,"val_bu":6200000,"total_vol":26000,"sum_vol":2000,"val":6200000,"acum_val":77140000,"datetime":1676641560000,"date":"2023-02-17T13:46:00.000Z","pbu":100,"psd":0,"puk":0,"bs":null,"sb":0,"abu":646.2,"asd":880.8,"auk":15.4,"rbu":3.1,"bu-sd":2000,"bu-sd_val":6200000,"avg_val_bu":1946153.8,"avg_val_sd":2564230.8,"acum_busd":-800,"acum_busd_val":-1140000,"acum_val_bu":37400000,"acum_val_sd":38540000,"rbusd":-10},{"c":3000,"h":3000,"l":3000,"o":3000,"bu":1000,"val_bu":3000000,"total_vol":27000,"sum_vol":1000,"val":3000000,"acum_val":80140000,"datetime":1676642040000,"date":"2023-02-17T13:54:00.000Z","pbu":100,"psd":0,"puk":0,"bs":null,"sb":0,"abu":646.2,"asd":880.8,"auk":15.4,"rbu":1.5,"bu-sd":1000,"bu-sd_val":3000000,"avg_val_bu":1946153.8,"avg_val_sd":2564230.8,"acum_busd":200,"acum_busd_val":1860000,"acum_val_bu":40400000,"acum_val_sd":38540000,"rbusd":-4.9},{"c":2900,"h":2900,"l":2900,"o":2900,"sd":5000,"val_sd":14500000,"total_vol":32000,"sum_vol":5000,"val":14500000,"acum_val":94640000,"datetime":1676643600000,"date":"2023-02-17T14:20:00.000Z","pbu":0,"psd":100,"puk":0,"bs":0,"sb":null,"abu":646.2,"asd":880.8,"auk":15.4,"rsd":5.7,"bu-sd":-5000,"bu-sd_val":-14500000,"avg_val_bu":1946153.8,"avg_val_sd":2564230.8,"acum_busd":-4800,"acum_busd_val":-12640000,"acum_val_bu":40400000,"acum_val_sd":53040000,"rbusd":23.5},{"c":2900,"h":3000,"l":2900,"o":3000,"bu":2000,"val_bu":6000000,"total_vol":37000,"sum_vol":5000,"val":14700000,"acum_val":109340000,"sd":3000,"val_sd":8700000,"datetime":1676644560000,"date":"2023-02-17T14:36:00.000Z","pbu":40,"psd":60,"puk":0,"bs":0.7,"sb":1.5,"abu":646.2,"asd":880.8,"auk":15.4,"rsd":3.4,"rbu":3.1,"bu-sd":-1000,"bu-sd_val":-2700000,"avg_val_bu":1946153.8,"avg_val_sd":2564230.8,"acum_busd":-5800,"acum_busd_val":-15340000,"acum_val_bu":46400000,"acum_val_sd":61740000,"rbusd":4.4},{"c":2900,"h":2900,"l":2900,"o":2900,"sd":1200,"val_sd":3480000,"total_vol":38200,"sum_vol":1200,"val":3480000,"acum_val":112820000,"datetime":1676644680000,"date":"2023-02-17T14:38:00.000Z","pbu":0,"psd":100,"puk":0,"bs":0,"sb":null,"abu":646.2,"asd":880.8,"auk":15.4,"rsd":1.4,"bu-sd":-1200,"bu-sd_val":-3480000,"avg_val_bu":1946153.8,"avg_val_sd":2564230.8,"acum_busd":-7000,"acum_busd_val":-18820000,"acum_val_bu":46400000,"acum_val_sd":65220000,"rbusd":5.6},{"c":2900,"h":2900,"l":2900,"o":2900,"sd":500,"val_sd":1450000,"total_vol":38700,"sum_vol":500,"val":1450000,"acum_val":114270000,"datetime":1676645520000,"date":"2023-02-17T14:52:00.000Z","pbu":0,"psd":100,"puk":0,"bs":0,"sb":null,"abu":646.2,"asd":880.8,"auk":15.4,"rsd":0.6,"bu-sd":-500,"bu-sd_val":-1450000,"avg_val_bu":1946153.8,"avg_val_sd":2564230.8,"acum_busd":-7500,"acum_busd_val":-20270000,"acum_val_bu":46400000,"acum_val_sd":66670000,"rbusd":2.3},{"c":3000,"h":3000,"l":3000,"o":3000,"bu":1000,"val_bu":3000000,"total_vol":39700,"sum_vol":1000,"val":3000000,"acum_val":117270000,"datetime":1676645640000,"date":"2023-02-17T14:54:00.000Z","pbu":100,"psd":0,"puk":0,"bs":null,"sb":0,"abu":646.2,"asd":880.8,"auk":15.4,"rbu":1.5,"bu-sd":1000,"bu-sd_val":3000000,"avg_val_bu":1946153.8,"avg_val_sd":2564230.8,"acum_busd":-6500,"acum_busd_val":-17270000,"acum_val_bu":49400000,"acum_val_sd":66670000,"rbusd":-4.9},{"c":3000,"h":3000,"l":3000,"o":3000,"bu":400,"val_bu":1200000,"total_vol":40100,"sum_vol":400,"val":1200000,"acum_val":118470000,"datetime":1676645880000,"date":"2023-02-17T14:58:00.000Z","pbu":100,"psd":0,"puk":0,"bs":null,"sb":0,"abu":646.2,"asd":880.8,"auk":15.4,"rbu":0.6,"bu-sd":400,"bu-sd_val":1200000,"avg_val_bu":1946153.8,"avg_val_sd":2564230.8,"acum_busd":-6100,"acum_busd_val":-16070000,"acum_val_bu":50600000,"acum_val_sd":66670000,"rbusd":-1.9}]