[{"c":5700,"change":-300,"pct":-5,"h":5700,"l":5700,"o":5700,"sd":1600,"val_sd":9120000,"total_vol":1600,"sum_vol":1600,"val":9120000,"acum_val":9120000,"datetime":1679478300000,"date":"2023-03-22T09:45:00.000Z","pbu":0,"psd":100,"puk":0,"bs":0,"sb":null,"abu":0,"asd":2760,"auk":0,"rsd":0.6,"bu-sd":-1600,"bu-sd_val":-9120000,"avg_val_bu":0,"avg_val_sd":16464000,"acum_busd":-1600,"acum_busd_val":-9120000,"acum_val_bu":0,"acum_val_sd":9120000,"rbusd":0.6,"meanc":2521.99,"stdc":2930.47,"Oc":-11474.38,"ORc":-4.55,"meanh":2522,"stdh":2930.47,"Oh":-11474.37,"ORh":-4.55,"meanl":2519.92,"stdl":2928.08,"Ol":-11460.37,"ORl":-4.55,"meano":2519.92,"stdo":2928.08,"Oo":-11460.36,"ORo":-4.55,"meanbu":910.36,"stdbu":2552.41,"Obu":-11851.71,"ORbu":-13.02,"meanval_bu":4070761.65,"stdval_bu":12091915.03,"Oval_bu":-56388813.52,"ORval_bu":-13.86,"meantotal_vol":7847.66,"stdtotal_vol":10740.43,"Ototal_vol":-47454.53,"ORtotal_vol":-6.05,"meansum_vol":2678.75,"stdsum_vol":4209.83,"Osum_vol":-19970.42,"ORsum_vol":-7.46,"meanval":13764307.77,"stdval":23549921.09,"Oval":-113105297.71,"ORval":-8.22,"meanacum_val":36606654.92,"stdacum_val":53036553.45,"Oacum_val":-237696112.38,"ORacum_val":-6.5,"meansd":1022.79,"stdsd":2293.67,"Osd":-10891.16,"ORsd":-10.65,"meanval_sd":5660624.87,"stdval_sd":12901190.01,"Oval_sd":-61046574.94,"ORval_sd":-10.79,"meanpbu":38.29,"stdpbu":47.88,"Opbu":-201.14,"ORpbu":-5.26,"meanpsd":39.39,"stdpsd":48.3,"Opsd":-180.9,"ORpsd":-4.6,"meanpuk":22.31,"stdpuk":41.05,"Opuk":-182.97,"ORpuk":-8.21,"meanbs":0.34,"stdbs":3.67,"Obs":-18.02,"ORbs":-52.76,"meansb":null,"stdsb":null,"Osb":null,"ORsb":-9007199254740991,"meanabu":910.36,"stdabu":1332.47,"Oabu":-5751.99,"ORabu":-6.32,"meanasd":1022.79,"stdasd":1448.98,"Oasd":-5507.74,"ORasd":-5.39,"meanauk":745.59,"stdauk":2080.88,"Oauk":-9658.82,"ORauk":-12.96,"meanrsd":0.78,"stdrsd":1.31,"Orsd":-6.39,"ORrsd":-8.15,"meanrbu":0.81,"stdrbu":1.32,"Orbu":-5.79,"ORrbu":-7.07,"meanbu-sd":-112.44,"stdbu-sd":3653.04,"Obu-sd":-16777.65,"ORbu-sd":-149.23,"meanbu-sd_val":-1589863.22,"stdbu-sd_val":18904367.04,"Obu-sd_val":-86991698.43,"ORbu-sd_val":-54.72,"meanacum_busd":-280.83,"stdacum_busd":8134.75,"Oacum_busd":-39354.63,"ORacum_busd":-140.14,"meanacum_busd_val":-7922467.36,"stdacum_busd_val":32594259.71,"Oacum_busd_val":-161773765.93,"ORacum_busd_val":-20.42,"meanacum_val_bu":10365597.92,"stdacum_val_bu":22756266.11,"Oacum_val_bu":-103415732.68,"ORacum_val_bu":-9.98,"meanacum_val_sd":18288065.28,"stdacum_val_sd":35157793.29,"Oacum_val_sd":-166620901.22,"ORacum_val_sd":-9.12,"meanrbusd":0.96,"stdrbusd":13.68,"Orbusd":-68.06,"ORrbusd":-70.36,"meanuk":745.59,"stduk":3086.27,"Ouk":-14685.77,"ORuk":-19.7,"meanval_uk":4032921.24,"stdval_uk":18336751.36,"Oval_uk":-87650835.57,"ORval_uk":-21.74,"meanruk":0.58,"stdruk":1.39,"Oruk":-6.37,"ORruk":-10.8,"BBmiddle":6045,"BBCmiddle":345,"BBupper":6564.519008314422,"BBCupper":864.5190083144216,"BBlower":5525.480991685578,"BBClower":-174.51900831442163,"BBpb":0.45669070882892004,"BBCpb":-5699.543309291171},{"c":6000,"change":0,"pct":0,"h":6000,"l":6000,"o":6000,"sd":2000,"val_sd":12000000,"total_vol":3600,"sum_vol":2000,"val":12000000,"acum_val":21120000,"datetime":1679492100000,"date":"2023-03-22T13:35:00.000Z","pbu":0,"psd":100,"puk":0,"bs":0,"sb":null,"abu":0,"asd":2760,"auk":0,"rsd":0.7,"bu-sd":-2000,"bu-sd_val":-12000000,"avg_val_bu":0,"avg_val_sd":16464000,"acum_busd":-3600,"acum_busd_val":-21120000,"acum_val_bu":0,"acum_val_sd":21120000,"rbusd":0.7,"meanc":2521.99,"stdc":2930.47,"Oc":-11174.38,"ORc":-4.44,"meanh":2522,"stdh":2930.47,"Oh":-11174.37,"ORh":-4.44,"meanl":2519.92,"stdl":2928.08,"Ol":-11160.37,"ORl":-4.43,"meano":2519.92,"stdo":2928.08,"Oo":-11160.36,"ORo":-4.43,"meanbu":910.36,"stdbu":2552.41,"Obu":-11851.71,"ORbu":-13.02,"meanval_bu":4070761.65,"stdval_bu":12091915.03,"Oval_bu":-56388813.52,"ORval_bu":-13.86,"meantotal_vol":7847.66,"stdtotal_vol":10740.43,"Ototal_vol":-49454.53,"ORtotal_vol":-6.31,"meansum_vol":2678.75,"stdsum_vol":4209.83,"Osum_vol":-20370.42,"ORsum_vol":-7.61,"meanval":13764307.77,"stdval":23549921.09,"Oval":-115985297.71,"ORval":-8.43,"meanacum_val":36606654.92,"stdacum_val":53036553.45,"Oacum_val":-249696112.38,"ORacum_val":-6.83,"meansd":1022.79,"stdsd":2293.67,"Osd":-10491.16,"ORsd":-10.26,"meanval_sd":5660624.87,"stdval_sd":12901190.01,"Oval_sd":-58166574.94,"ORval_sd":-10.28,"meanpbu":38.29,"stdpbu":47.88,"Opbu":-201.14,"ORpbu":-5.26,"meanpsd":39.39,"stdpsd":48.3,"Opsd":-180.9,"ORpsd":-4.6,"meanpuk":22.31,"stdpuk":41.05,"Opuk":-182.97,"ORpuk":-8.21,"meanbs":0.34,"stdbs":3.67,"Obs":-18.02,"ORbs":-52.76,"meansb":null,"stdsb":null,"Osb":null,"ORsb":-9007199254740991,"meanabu":910.36,"stdabu":1332.47,"Oabu":-5751.99,"ORabu":-6.32,"meanasd":1022.79,"stdasd":1448.98,"Oasd":-5507.74,"ORasd":-5.39,"meanauk":745.59,"stdauk":2080.88,"Oauk":-9658.82,"ORauk":-12.96,"meanrsd":0.78,"stdrsd":1.31,"Orsd":-6.49,"ORrsd":-8.28,"meanrbu":0.81,"stdrbu":1.32,"Orbu":-5.79,"ORrbu":-7.07,"meanbu-sd":-112.44,"stdbu-sd":3653.04,"Obu-sd":-16377.65,"ORbu-sd":-145.67,"meanbu-sd_val":-1589863.22,"stdbu-sd_val":18904367.04,"Obu-sd_val":-84111698.43,"ORbu-sd_val":-52.91,"meanacum_busd":-280.83,"stdacum_busd":8134.75,"Oacum_busd":-37354.63,"ORacum_busd":-133.02,"meanacum_busd_val":-7922467.36,"stdacum_busd_val":32594259.71,"Oacum_busd_val":-149773765.93,"ORacum_busd_val":-18.91,"meanacum_val_bu":10365597.92,"stdacum_val_bu":22756266.11,"Oacum_val_bu":-103415732.68,"ORacum_val_bu":-9.98,"meanacum_val_sd":18288065.28,"stdacum_val_sd":35157793.29,"Oacum_val_sd":-172957031.79,"ORacum_val_sd":-9.46,"meanrbusd":0.96,"stdrbusd":13.68,"Orbusd":-68.16,"ORrbusd":-70.46,"meanuk":745.59,"stduk":3086.27,"Ouk":-14685.77,"ORuk":-19.7,"meanval_uk":4032921.24,"stdval_uk":18336751.36,"Oval_uk":-87650835.57,"ORval_uk":-21.74,"meanruk":0.58,"stdruk":1.39,"Oruk":-6.37,"ORruk":-10.8,"BBmiddle":6030,"BBCmiddle":30,"BBupper":6570.740233383831,"BBCupper":570.7402333838309,"BBlower":5489.259766616169,"BBClower":-510.74023338383086,"BBpb":0.1948627273996849,"BBCpb":-5999.8051372726},{"c":6000,"change":0,"pct":0,"h":6000,"l":6000,"o":6000,"sd":1200,"val_sd":7200000,"total_vol":4800,"sum_vol":1200,"val":7200000,"acum_val":28320000,"datetime":1679492700000,"date":"2023-03-22T13:45:00.000Z","pbu":0,"psd":100,"puk":0,"bs":0,"sb":null,"abu":0,"asd":2760,"auk":0,"rsd":0.4,"bu-sd":-1200,"bu-sd_val":-7200000,"avg_val_bu":0,"avg_val_sd":16464000,"acum_busd":-4800,"acum_busd_val":-28320000,"acum_val_bu":0,"acum_val_sd":28320000,"rbusd":0.4,"meanc":2521.99,"stdc":2930.47,"Oc":-11174.38,"ORc":-4.44,"meanh":2522,"stdh":2930.47,"Oh":-11174.37,"ORh":-4.44,"meanl":2519.92,"stdl":2928.08,"Ol":-11160.37,"ORl":-4.43,"meano":2519.92,"stdo":2928.08,"Oo":-11160.36,"ORo":-4.43,"meanbu":910.36,"stdbu":2552.41,"Obu":-11851.71,"ORbu":-13.02,"meanval_bu":4070761.65,"stdval_bu":12091915.03,"Oval_bu":-56388813.52,"ORval_bu":-13.86,"meantotal_vol":7847.66,"stdtotal_vol":10740.43,"Ototal_vol":-50654.53,"ORtotal_vol":-6.46,"meansum_vol":2678.75,"stdsum_vol":4209.83,"Osum_vol":-19570.42,"ORsum_vol":-7.31,"meanval":13764307.77,"stdval":23549921.09,"Oval":-111185297.71,"ORval":-8.08,"meanacum_val":36606654.92,"stdacum_val":53036553.45,"Oacum_val":-256896112.38,"ORacum_val":-7.02,"meansd":1022.79,"stdsd":2293.67,"Osd":-11291.16,"ORsd":-11.04,"meanval_sd":5660624.87,"stdval_sd":12901190.01,"Oval_sd":-62966574.94,"ORval_sd":-11.13,"meanpbu":38.29,"stdpbu":47.88,"Opbu":-201.14,"ORpbu":-5.26,"meanpsd":39.39,"stdpsd":48.3,"Opsd":-180.9,"ORpsd":-4.6,"meanpuk":22.31,"stdpuk":41.05,"Opuk":-182.97,"ORpuk":-8.21,"meanbs":0.34,"stdbs":3.67,"Obs":-18.02,"ORbs":-52.76,"meansb":null,"stdsb":null,"Osb":null,"ORsb":-9007199254740991,"meanabu":910.36,"stdabu":1332.47,"Oabu":-5751.99,"ORabu":-6.32,"meanasd":1022.79,"stdasd":1448.98,"Oasd":-5507.74,"ORasd":-5.39,"meanauk":745.59,"stdauk":2080.88,"Oauk":-9658.82,"ORauk":-12.96,"meanrsd":0.78,"stdrsd":1.31,"Orsd":-6.19,"ORrsd":-7.9,"meanrbu":0.81,"stdrbu":1.32,"Orbu":-5.79,"ORrbu":-7.07,"meanbu-sd":-112.44,"stdbu-sd":3653.04,"Obu-sd":-17177.65,"ORbu-sd":-152.78,"meanbu-sd_val":-1589863.22,"stdbu-sd_val":18904367.04,"Obu-sd_val":-88911698.43,"ORbu-sd_val":-55.93,"meanacum_busd":-280.83,"stdacum_busd":8134.75,"Oacum_busd":-36154.63,"ORacum_busd":-128.75,"meanacum_busd_val":-7922467.36,"stdacum_busd_val":32594259.71,"Oacum_busd_val":-142573765.93,"ORacum_busd_val":-18,"meanacum_val_bu":10365597.92,"stdacum_val_bu":22756266.11,"Oacum_val_bu":-103415732.68,"ORacum_val_bu":-9.98,"meanacum_val_sd":18288065.28,"stdacum_val_sd":35157793.29,"Oacum_val_sd":-165757031.79,"ORacum_val_sd":-9.07,"meanrbusd":0.96,"stdrbusd":13.68,"Orbusd":-67.86,"ORrbusd":-70.15,"meanuk":745.59,"stduk":3086.27,"Ouk":-14685.77,"ORuk":-19.7,"meanval_uk":4032921.24,"stdval_uk":18336751.36,"Oval_uk":-87650835.57,"ORval_uk":-21.74,"meanruk":0.58,"stdruk":1.39,"Oruk":-6.37,"ORruk":-10.8,"BBmiddle":6045,"BBCmiddle":45,"BBupper":6564.519008314422,"BBCupper":564.5190083144216,"BBlower":5525.480991685578,"BBClower":-474.5190083144216,"BBpb":0.45669070882892004,"BBCpb":-5999.543309291171},{"c":6000,"change":0,"pct":0,"h":6000,"l":6000,"o":6000,"sd":6000,"val_sd":36000000,"total_vol":10800,"sum_vol":6000,"val":36000000,"acum_val":64320000,"datetime":1679493300000,"date":"2023-03-22T13:55:00.000Z","pbu":0,"psd":100,"puk":0,"bs":0,"sb":null,"abu":0,"asd":2760,"auk":0,"rsd":2.2,"bu-sd":-6000,"bu-sd_val":-36000000,"avg_val_bu":0,"avg_val_sd":16464000,"acum_busd":-10800,"acum_busd_val":-64320000,"acum_val_bu":0,"acum_val_sd":64320000,"rbusd":2.2,"meanc":2521.99,"stdc":2930.47,"Oc":-11174.38,"ORc":-4.44,"meanh":2522,"stdh":2930.47,"Oh":-11174.37,"ORh":-4.44,"meanl":2519.92,"stdl":2928.08,"Ol":-11160.37,"ORl":-4.43,"meano":2519.92,"stdo":2928.08,"Oo":-11160.36,"ORo":-4.43,"meanbu":910.36,"stdbu":2552.41,"Obu":-11851.71,"ORbu":-13.02,"meanval_bu":4070761.65,"stdval_bu":12091915.03,"Oval_bu":-56388813.52,"ORval_bu":-13.86,"meantotal_vol":7847.66,"stdtotal_vol":10740.43,"Ototal_vol":-50749.86,"ORtotal_vol":-6.47,"meansum_vol":2678.75,"stdsum_vol":4209.83,"Osum_vol":-17727.94,"ORsum_vol":-6.62,"meanval":13764307.77,"stdval":23549921.09,"Oval":-95513913.26,"ORval":-6.94,"meanacum_val":36606654.92,"stdacum_val":53036553.45,"Oacum_val":-237469422.22,"ORacum_val":-6.49,"meansd":1022.79,"stdsd":2293.67,"Osd":-6491.16,"ORsd":-6.35,"meanval_sd":5660624.87,"stdval_sd":12901190.01,"Oval_sd":-34166574.94,"ORval_sd":-6.04,"meanpbu":38.29,"stdpbu":47.88,"Opbu":-201.14,"ORpbu":-5.26,"meanpsd":39.39,"stdpsd":48.3,"Opsd":-180.9,"ORpsd":-4.6,"meanpuk":22.31,"stdpuk":41.05,"Opuk":-182.97,"ORpuk":-8.21,"meanbs":0.34,"stdbs":3.67,"Obs":-18.02,"ORbs":-52.76,"meansb":null,"stdsb":null,"Osb":null,"ORsb":-9007199254740991,"meanabu":910.36,"stdabu":1332.47,"Oabu":-5751.99,"ORabu":-6.32,"meanasd":1022.79,"stdasd":1448.98,"Oasd":-5507.74,"ORasd":-5.39,"meanauk":745.59,"stdauk":2080.88,"Oauk":-9658.82,"ORauk":-12.96,"meanrsd":0.78,"stdrsd":1.31,"Orsd":-5.16,"ORrsd":-6.58,"meanrbu":0.81,"stdrbu":1.32,"Orbu":-5.79,"ORrbu":-7.07,"meanbu-sd":-112.44,"stdbu-sd":3653.04,"Obu-sd":-12377.65,"ORbu-sd":-110.09,"meanbu-sd_val":-1589863.22,"stdbu-sd_val":18904367.04,"Obu-sd_val":-60111698.43,"ORbu-sd_val":-37.81,"meanacum_busd":-280.83,"stdacum_busd":8134.75,"Oacum_busd":-30154.63,"ORacum_busd":-107.38,"meanacum_busd_val":-7922467.36,"stdacum_busd_val":32594259.71,"Oacum_busd_val":-106573765.93,"ORacum_busd_val":-13.46,"meanacum_val_bu":10365597.92,"stdacum_val_bu":22756266.11,"Oacum_val_bu":-103415732.68,"ORacum_val_bu":-9.98,"meanacum_val_sd":18288065.28,"stdacum_val_sd":35157793.29,"Oacum_val_sd":-129757031.79,"ORacum_val_sd":-7.1,"meanrbusd":0.96,"stdrbusd":13.68,"Orbusd":-67.2,"ORrbusd":-69.46,"meanuk":745.59,"stduk":3086.27,"Ouk":-14685.77,"ORuk":-19.7,"meanval_uk":4032921.24,"stdval_uk":18336751.36,"Oval_uk":-87650835.57,"ORval_uk":-21.74,"meanruk":0.58,"stdruk":1.39,"Oruk":-6.37,"ORruk":-10.8,"BBmiddle":6045,"BBCmiddle":45,"BBupper":6564.519008314422,"BBCupper":564.5190083144216,"BBlower":5525.480991685578,"BBClower":-474.5190083144216,"BBpb":0.45669070882892004,"BBCpb":-5999.543309291171},{"c":6000,"change":0,"pct":0,"h":6000,"l":6000,"o":6000,"sd":3000,"val_sd":18000000,"total_vol":13800,"sum_vol":3000,"val":18000000,"acum_val":82320000,"datetime":1679493900000,"date":"2023-03-22T14:05:00.000Z","pbu":0,"psd":100,"puk":0,"bs":0,"sb":null,"abu":0,"asd":2760,"auk":0,"rsd":1.1,"bu-sd":-3000,"bu-sd_val":-18000000,"avg_val_bu":0,"avg_val_sd":16464000,"acum_busd":-13800,"acum_busd_val":-82320000,"acum_val_bu":0,"acum_val_sd":82320000,"rbusd":1.1,"meanc":2521.99,"stdc":2930.47,"Oc":-11174.38,"ORc":-4.44,"meanh":2522,"stdh":2930.47,"Oh":-11174.37,"ORh":-4.44,"meanl":2519.92,"stdl":2928.08,"Ol":-11160.37,"ORl":-4.43,"meano":2519.92,"stdo":2928.08,"Oo":-11160.36,"ORo":-4.43,"meanbu":910.36,"stdbu":2552.41,"Obu":-11851.71,"ORbu":-13.02,"meanval_bu":4070761.65,"stdval_bu":12091915.03,"Oval_bu":-56388813.52,"ORval_bu":-13.86,"meantotal_vol":7847.66,"stdtotal_vol":10740.43,"Ototal_vol":-47749.86,"ORtotal_vol":-6.09,"meansum_vol":2678.75,"stdsum_vol":4209.83,"Osum_vol":-20727.94,"ORsum_vol":-7.74,"meanval":13764307.77,"stdval":23549921.09,"Oval":-113513913.26,"ORval":-8.25,"meanacum_val":36606654.92,"stdacum_val":53036553.45,"Oacum_val":-219469422.22,"ORacum_val":-6,"meansd":1022.79,"stdsd":2293.67,"Osd":-9491.16,"ORsd":-9.28,"meanval_sd":5660624.87,"stdval_sd":12901190.01,"Oval_sd":-52166574.94,"ORval_sd":-9.22,"meanpbu":38.29,"stdpbu":47.88,"Opbu":-201.14,"ORpbu":-5.26,"meanpsd":39.39,"stdpsd":48.3,"Opsd":-180.9,"ORpsd":-4.6,"meanpuk":22.31,"stdpuk":41.05,"Opuk":-182.97,"ORpuk":-8.21,"meanbs":0.34,"stdbs":3.67,"Obs":-18.02,"ORbs":-52.76,"meansb":null,"stdsb":null,"Osb":null,"ORsb":-9007199254740991,"meanabu":910.36,"stdabu":1332.47,"Oabu":-5751.99,"ORabu":-6.32,"meanasd":1022.79,"stdasd":1448.98,"Oasd":-5507.74,"ORasd":-5.39,"meanauk":745.59,"stdauk":2080.88,"Oauk":-9658.82,"ORauk":-12.96,"meanrsd":0.78,"stdrsd":1.31,"Orsd":-6.26,"ORrsd":-7.98,"meanrbu":0.81,"stdrbu":1.32,"Orbu":-5.79,"ORrbu":-7.07,"meanbu-sd":-112.44,"stdbu-sd":3653.04,"Obu-sd":-15377.65,"ORbu-sd":-136.77,"meanbu-sd_val":-1589863.22,"stdbu-sd_val":18904367.04,"Obu-sd_val":-78111698.43,"ORbu-sd_val":-49.14,"meanacum_busd":-280.83,"stdacum_busd":8134.75,"Oacum_busd":-27154.63,"ORacum_busd":-96.7,"meanacum_busd_val":-7922467.36,"stdacum_busd_val":32594259.71,"Oacum_busd_val":-88573765.93,"ORacum_busd_val":-11.19,"meanacum_val_bu":10365597.92,"stdacum_val_bu":22756266.11,"Oacum_val_bu":-103415732.68,"ORacum_val_bu":-9.98,"meanacum_val_sd":18288065.28,"stdacum_val_sd":35157793.29,"Oacum_val_sd":-111757031.79,"ORacum_val_sd":-6.12,"meanrbusd":0.96,"stdrbusd":13.68,"Orbusd":-68.3,"ORrbusd":-70.6,"meanuk":745.59,"stduk":3086.27,"Ouk":-14685.77,"ORuk":-19.7,"meanval_uk":4032921.24,"stdval_uk":18336751.36,"Oval_uk":-87650835.57,"ORval_uk":-21.74,"meanruk":0.58,"stdruk":1.39,"Oruk":-6.37,"ORruk":-10.8,"BBmiddle":6045,"BBCmiddle":45,"BBupper":6564.519008314422,"BBCupper":564.5190083144216,"BBlower":5525.480991685578,"BBClower":-474.5190083144216,"BBpb":0.16796210102172027,"BBCpb":-5999.832037898978}]