[{"c":10.35,"h":10.35,"l":10.35,"o":10.35,"sd":500,"val_sd":5175000,"total_vol":500,"sum_vol":500,"val":5175000,"acum_val":5175000,"datetime":1671182100000,"date":"2022-12-16T09:15:00.000Z","pbu":0,"psd":100,"puk":0,"bs":0,"sb":null,"abu":353.8,"asd":146.2,"auk":84.6,"rsd":3.4,"bu-sd":-500,"bu-sd_val":-5175000,"acum_busd":-500,"acum_busd_val":-5175000},{"c":10.15,"h":10.15,"l":10.15,"o":10.15,"sd":300,"val_sd":3045000,"total_vol":800,"sum_vol":300,"val":3045000,"acum_val":8220000,"datetime":1671183900000,"date":"2022-12-16T09:45:00.000Z","pbu":0,"psd":100,"puk":0,"bs":0,"sb":null,"abu":353.8,"asd":146.2,"auk":84.6,"rsd":2.1,"bu-sd":-300,"bu-sd_val":-3045000,"acum_busd":-800,"acum_busd_val":-8220000},{"c":10.5,"h":10.5,"l":10.5,"o":10.5,"bu":100,"val_bu":1050000,"total_vol":900,"sum_vol":100,"val":1050000,"acum_val":9270000,"datetime":1671186300000,"date":"2022-12-16T10:25:00.000Z","pbu":100,"psd":0,"puk":0,"bs":null,"sb":0,"abu":353.8,"asd":146.2,"auk":84.6,"rbu":0.3,"bu-sd":100,"bu-sd_val":1050000,"acum_busd":-700,"acum_busd_val":-7170000},{"c":10.55,"h":10.55,"l":10.55,"o":10.55,"uk":200,"val_uk":2110000,"total_vol":1100,"sum_vol":200,"val":2110000,"acum_val":11380000,"datetime":1671186600000,"date":"2022-12-16T10:30:00.000Z","pbu":0,"psd":0,"puk":100,"bs":null,"sb":null,"abu":353.8,"asd":146.2,"auk":84.6,"ruk":2.4,"bu-sd":0,"bu-sd_val":0,"acum_busd":-700,"acum_busd_val":-7170000},{"c":10.55,"h":10.55,"l":10.55,"o":10.55,"sd":600,"val_sd":6330000,"total_vol":1700,"sum_vol":600,"val":6330000,"acum_val":17710000,"datetime":1671187500000,"date":"2022-12-16T10:45:00.000Z","pbu":0,"psd":100,"puk":0,"bs":0,"sb":null,"abu":353.8,"asd":146.2,"auk":84.6,"rsd":4.1,"bu-sd":-600,"bu-sd_val":-6330000,"acum_busd":-1300,"acum_busd_val":-13500000},{"c":10.55,"h":10.55,"l":10.55,"o":10.55,"sd":400,"val_sd":4220000,"total_vol":2100,"sum_vol":400,"val":4220000,"acum_val":21930000,"datetime":1671187800000,"date":"2022-12-16T10:50:00.000Z","pbu":0,"psd":100,"puk":0,"bs":0,"sb":null,"abu":353.8,"asd":146.2,"auk":84.6,"rsd":2.7,"bu-sd":-400,"bu-sd_val":-4220000,"acum_busd":-1700,"acum_busd_val":-17720000},{"c":10.55,"h":10.55,"l":10.55,"o":10.55,"bu":2200,"val_bu":23210000,"total_vol":4300,"sum_vol":2200,"val":23210000,"acum_val":45140000,"datetime":1671195600000,"date":"2022-12-16T13:00:00.000Z","pbu":100,"psd":0,"puk":0,"bs":null,"sb":0,"abu":353.8,"asd":146.2,"auk":84.6,"rbu":6.2,"bu-sd":2200,"bu-sd_val":23210000,"acum_busd":500,"acum_busd_val":5490000},{"c":10.55,"h":10.55,"l":10.55,"o":10.55,"bu":900,"val_bu":9495000,"total_vol":5300,"sum_vol":1000,"val":10550000,"acum_val":55690000,"sd":100,"val_sd":1055000,"datetime":1671195900000,"date":"2022-12-16T13:05:00.000Z","pbu":90,"psd":10,"puk":0,"bs":9,"sb":0.1,"abu":353.8,"asd":146.2,"auk":84.6,"rsd":0.7,"rbu":2.5,"bu-sd":800,"bu-sd_val":8440000,"acum_busd":1300,"acum_busd_val":13930000},{"c":10.5,"h":10.5,"l":10.5,"o":10.5,"bu":500,"val_bu":5250000,"total_vol":5800,"sum_vol":500,"val":5250000,"acum_val":60940000,"datetime":1671196800000,"date":"2022-12-16T13:20:00.000Z","pbu":100,"psd":0,"puk":0,"bs":null,"sb":0,"abu":353.8,"asd":146.2,"auk":84.6,"rbu":1.4,"bu-sd":500,"bu-sd_val":5250000,"acum_busd":1800,"acum_busd_val":19180000},{"c":10.5,"h":10.5,"l":10.5,"o":10.5,"bu":100,"val_bu":1050000,"total_vol":5900,"sum_vol":100,"val":1050000,"acum_val":61990000,"datetime":1671198600000,"date":"2022-12-16T13:50:00.000Z","pbu":100,"psd":0,"puk":0,"bs":null,"sb":0,"abu":353.8,"asd":146.2,"auk":84.6,"rbu":0.3,"bu-sd":100,"bu-sd_val":1050000,"acum_busd":1900,"acum_busd_val":20230000},{"c":10.5,"h":10.5,"l":10.5,"o":10.5,"bu":700,"val_bu":7350000,"total_vol":6600,"sum_vol":700,"val":7350000,"acum_val":69340000,"datetime":1671200100000,"date":"2022-12-16T14:15:00.000Z","pbu":100,"psd":0,"puk":0,"bs":null,"sb":0,"abu":353.8,"asd":146.2,"auk":84.6,"rbu":2,"bu-sd":700,"bu-sd_val":7350000,"acum_busd":2600,"acum_busd_val":27580000},{"c":10.5,"h":10.5,"l":10.5,"o":10.5,"bu":100,"val_bu":1050000,"total_vol":6700,"sum_vol":100,"val":1050000,"acum_val":70390000,"datetime":1671200700000,"date":"2022-12-16T14:25:00.000Z","pbu":100,"psd":0,"puk":0,"bs":null,"sb":0,"abu":353.8,"asd":146.2,"auk":84.6,"rbu":0.3,"bu-sd":100,"bu-sd_val":1050000,"acum_busd":2700,"acum_busd_val":28630000},{"c":10.2,"h":10.2,"l":10.2,"o":10.2,"uk":900,"val_uk":9180000,"total_vol":7600,"sum_vol":900,"val":9180000,"acum_val":79570000,"datetime":1671201900000,"date":"2022-12-16T14:45:00.000Z","pbu":0,"psd":0,"puk":100,"bs":null,"sb":null,"abu":353.8,"asd":146.2,"auk":84.6,"ruk":10.6,"bu-sd":0,"bu-sd_val":0,"acum_busd":2700,"acum_busd_val":28630000}]