[{"c":11.9,"h":11.9,"l":11.9,"o":11.9,"bu":2300,"val_bu":27370000,"total_vol":2300,"sum_vol":2300,"val":27370000,"acum_val":27370000,"datetime":1671448440000,"date":"2022-12-19T11:14:00.000Z","pbu":100,"psd":0,"puk":0,"bs":null,"sb":0,"abu":1150,"asd":100,"auk":0,"rbu":2,"bu-sd":2300,"bu-sd_val":27370000,"avg_val_bu":13685000,"avg_val_sd":1190000,"acum_busd":2300,"acum_busd_val":27370000,"acum_val_bu":27370000,"acum_val_sd":0,"rbusd":2.2},{"c":11.9,"h":11.9,"l":11.9,"o":11.9,"sd":200,"val_sd":2380000,"total_vol":2500,"sum_vol":200,"val":2380000,"acum_val":29750000,"datetime":1671455280000,"date":"2022-12-19T13:08:00.000Z","pbu":0,"psd":100,"puk":0,"bs":0,"sb":null,"abu":1150,"asd":100,"auk":0,"rsd":2,"bu-sd":-200,"bu-sd_val":-2380000,"avg_val_bu":13685000,"avg_val_sd":1190000,"acum_busd":2100,"acum_busd_val":24990000,"acum_val_bu":27370000,"acum_val_sd":2380000,"rbusd":0.2}]